<?xml version="1.0" ?><witnesses>
	<block n="0">
		<token n="с" u="80,14." witness="#aka">сеи</token>
		<token n="се" u="80,14." witness="#bych">се</token>
		<token n="с" u="80,14." witness="#ipa">сь</token>
		<token n="с" u="80,14." witness="#kom">сеи</token>
		<token n="се" u="80,14." witness="#lav">се</token>
		<token n="с" u="80,14." witness="#lem">Сь</token>
		<token n="се" u="80,14." witness="#likh">се</token>
		<token n="с" u="80,14." witness="#nak">сеи</token>
		<token n="се" u="80,14." witness="#rad">се</token>
		<token n="с" u="80,14." witness="#shakh">сь</token>
		<token n="с" u="80,14." witness="#tol">сеи</token>
		<token n="с" u="80,14." witness="#xle">се<hi rend="sup">и</hi></token>
	</block>
	<block n="1">
		<token n="же" u="80,14." witness="#aka">же</token>
		<token n="же" u="80,14." witness="#bych">же</token>
		<token n="же" u="80,14." witness="#ipa">же</token>
		<token n="же" u="80,14." witness="#kom">же</token>
		<token n="же" u="80,14." witness="#lav">же</token>
		<token n="же" u="80,14." witness="#lem">же</token>
		<token n="же" u="80,14." witness="#likh">же</token>
		<token n="же" u="80,14." witness="#nak">же</token>
		<token n="же" u="80,14." witness="#rad">же</token>
		<token n="же" u="80,14." witness="#shakh">же</token>
		<token n="же" u="80,14." witness="#tol">же</token>
		<token n="же" u="80,14." witness="#xle">же</token>
	</block>
	<block n="2">
		<token n="бѣ" u="80,14." witness="#aka">бѣ</token>
		<token n="бѣ" u="80,14." witness="#bych">бѣ</token>
		<token n="бѣ" u="80,14." witness="#ipa">бѣ <lb/></token>
		<token n="бѣ" u="80,14." witness="#kom">бѣ</token>
		<token n="бѣ" u="80,14." witness="#lav">бѣ</token>
		<token n="бѣ" u="80,14." witness="#lem">бѣ</token>
		<token n="бѣ" u="80,14." witness="#likh">бѣ</token>
		<token n="бѣ" u="80,14." witness="#nak">бѣ</token>
		<token n="бѣ" u="80,14." witness="#rad">бѣ</token>
		<token n="бѣ" u="80,14." witness="#shakh">бѣ</token>
		<token n="бѣ" u="80,14." witness="#tol">бѣ</token>
		<token n="бѣ" u="80,14." witness="#xle">бѣ</token>
	</block>
	<block n="3">
		<token n="нвгл" u="80,14." witness="#aka">невѣигласъ.</token>
		<token n="нвгл" u="80,14." witness="#bych">невѣголосъ,</token>
		<token n="нвгл" u="80,14." witness="#ipa">невегла<hi rend="sup">с</hi>.</token>
		<token n="нвгл" u="80,14." witness="#kom">невѣглас</token>
		<token n="нвгл" u="80,14." witness="#lav">невѣголосъ.</token>
		<token n="нвгл" u="80,14." witness="#lem">невѣгласъ,</token>
		<token n="нвгл" u="80,14." witness="#likh">невѣголосъ,</token>
		<token n="нвгл" u="80,14." witness="#nak">невѣглас</token>
		<token n="нвгл" u="80,14." witness="#rad">невѣигла<hi rend="sup">с</hi>.</token>
		<token n="нвгл" u="80,14." witness="#shakh">невѣгласъ,</token>
		<token n="нвгл" u="80,14." witness="#tol">невѣглас</token>
		<token n="нвгл" u="80,14." witness="#xle">невѣгла<hi rend="sup">с</hi>,</token>
	</block>
	<block n="4">
		<token n="а" u="80,14." witness="#aka">а</token>
		<token n="а" u="80,14." witness="#bych">а</token>
		<token n="" u="80,14." witness="#ipa"/>
		<token n="а" u="80,14." witness="#kom">а</token>
		<token n="а" u="80,14." witness="#lav">а</token>
		<token n="а" u="80,14." witness="#lem">а</token>
		<token n="а" u="80,14." witness="#likh">а</token>
		<token n="а" u="80,14." witness="#nak">а</token>
		<token n="а" u="80,14." witness="#rad">а</token>
		<token n="а" u="80,14." witness="#shakh">а</token>
		<token n="а" u="80,14." witness="#tol">а</token>
		<token n="а" u="80,14." witness="#xle">а</token>
	</block>
	<block n="5">
		<token n="на" u="80,14." witness="#aka">на</token>
		<token n="" u="80,14." witness="#bych"/>
		<token n="на" u="80,14." witness="#ipa">на</token>
		<token n="на" u="80,14." witness="#kom">на</token>
		<token n="на" u="80,14." witness="#lav">на</token>
		<token n="на" u="80,14." witness="#lem">на</token>
		<token n="" u="80,14." witness="#likh"/>
		<token n="на" u="80,14." witness="#nak">на</token>
		<token n="на" u="80,14." witness="#rad">на</token>
		<token n="на" u="80,14." witness="#shakh">на</token>
		<token n="на" u="80,14." witness="#tol">на</token>
		<token n="на" u="80,14." witness="#xle">на</token>
	</block>
	<block n="6">
		<token n="кнц" u="80,14." witness="#aka">конець</token>
		<token n="нкнц" u="80,14." witness="#bych">наконець</token>
		<token n="кнц" u="80,14." witness="#ipa">конѣць</token>
		<token n="кнц" u="80,14." witness="#kom">конець</token>
		<token n="кнц" u="80,14." witness="#lav">конець</token>
		<token n="кнц" u="80,14." witness="#lem">коньць</token>
		<token n="нкнц" u="80,14." witness="#likh">наконець</token>
		<token n="кнц" u="80,14." witness="#nak">конець</token>
		<token n="кнц" u="80,14." witness="#rad">конець</token>
		<token n="кнц" u="80,14." witness="#shakh">коньць</token>
		<token n="кнц" u="80,14." witness="#tol">конець</token>
		<token n="кнц" u="80,14." witness="#xle">конець</token>
	</block>
	<block n="7">
		<token n="обрт" u="80,14." witness="#aka">ѡбрѣте <lb/></token>
		<token n="обрт" u="80,14." witness="#bych">обрѣте</token>
		<token n="обрт" u="80,14." witness="#ipa">ѡбрѣ<lb/>те</token>
		<token n="обрт" u="80,14." witness="#kom">обрѣте</token>
		<token n="обрт" u="80,14." witness="#lav">ѡбрѣте</token>
		<token n="обрт" u="80,14." witness="#lem">обрѣте</token>
		<token n="обрт" u="80,14." witness="#likh">обрѣте</token>
		<token n="обрт" u="80,14." witness="#nak">обрѣте</token>
		<token n="обрт" u="80,14." witness="#rad">ѡбрѣте <pb n="45v"/></token>
		<token n="обрт" u="80,14." witness="#shakh">обрѣте</token>
		<token n="обрт" u="80,14." witness="#tol">обрѣте</token>
		<token n="обрт" u="80,14." witness="#xle">обрѣте</token>
	</block>
</witnesses>