<?xml version="1.0" ?><witnesses>
	<block n="0">
		<token n="" u="181,21." witness="#aka"/>
		<token n="бѣ" u="181,21." witness="#bych">бѣ,</token>
		<token n="же" u="181,21." witness="#ipa">же</token>
		<token n="же" u="181,21." witness="#kom">же</token>
		<token n="бѣ" u="181,21." witness="#lav">бѣ.</token>
		<token n="же" u="181,21." witness="#lem">же</token>
		<token n="бѣ" u="181,21." witness="#likh">бѣ</token>
		<token n="бѣ" u="181,21." witness="#nak">бѣ</token>
		<token n="" u="181,21." witness="#rad"/>
		<token n="бѣ" u="181,21." witness="#shakh">бѣ</token>
		<token n="бѣ" u="181,21." witness="#tol">бѣ</token>
		<token n="же" u="181,21." witness="#xle">же</token>
	</block>
	<block n="1">
		<token n="" u="181,21." witness="#aka"/>
		<token n="" u="181,21." witness="#bych"/>
		<token n="бѣ" u="181,21." witness="#ipa">бѣ <lb/></token>
		<token n="бѣ" u="181,21." witness="#kom">бѣ</token>
		<token n="" u="181,21." witness="#lav"/>
		<token n="бѣ" u="181,21." witness="#lem">бѣ</token>
		<token n="" u="181,21." witness="#likh"/>
		<token n="" u="181,21." witness="#nak"/>
		<token n="" u="181,21." witness="#rad"/>
		<token n="" u="181,21." witness="#shakh"/>
		<token n="" u="181,21." witness="#tol"/>
		<token n="бѣ" u="181,21." witness="#xle">бѣ</token>
	</block>
	<block n="2">
		<token n="" u="181,21." witness="#aka"/>
		<token n="тгд" u="181,21." witness="#bych">тогда</token>
		<token n="" u="181,21." witness="#ipa"/>
		<token n="в" u="181,21." witness="#kom">в</token>
		<token n="тгд" u="181,21." witness="#lav">тогда</token>
		<token n="" u="181,21." witness="#lem"/>
		<token n="тгд" u="181,21." witness="#likh">тогда</token>
		<token n="тгд" u="181,21." witness="#nak">тъгда</token>
		<token n="ггр" u="181,21." witness="#rad">геѡгрии.</token>
		<token n="тгд" u="181,21." witness="#shakh">тъгда</token>
		<token n="тгд" u="181,21." witness="#tol">тъгда</token>
		<token n="" u="181,21." witness="#xle"><hi rend="sup">д</hi></token>
	</block>
	<block n="3">
		<token n="" u="181,21." witness="#aka"/>
		<token n="" u="181,21." witness="#bych"/>
		<token n="тгд" u="181,21." witness="#ipa">тогда</token>
		<token n="то" u="181,21." witness="#kom">то</token>
		<token n="" u="181,21." witness="#lav"/>
		<token n="тгд" u="181,21." witness="#lem">тъгда</token>
		<token n="" u="181,21." witness="#likh"/>
		<token n="" u="181,21." witness="#nak"/>
		<token n="" u="181,21." witness="#rad"/>
		<token n="" u="181,21." witness="#shakh"/>
		<token n="" u="181,21." witness="#tol"/>
		<token n="тгд" u="181,21." witness="#xle">тог<hi rend="sup">д</hi>а</token>
	</block>
	<block n="4">
		<token n="" u="181,21." witness="#aka"/>
		<token n="" u="181,21." witness="#bych"/>
		<token n="" u="181,21." witness="#ipa"/>
		<token n="врм" u="181,21." witness="#kom">времꙗ</token>
		<token n="" u="181,21." witness="#lav"/>
		<token n="" u="181,21." witness="#lem"/>
		<token n="" u="181,21." witness="#likh"/>
		<token n="" u="181,21." witness="#nak"/>
		<token n="" u="181,21." witness="#rad"/>
		<token n="" u="181,21." witness="#shakh"/>
		<token n="" u="181,21." witness="#tol"/>
		<token n="" u="181,21." witness="#xle"/>
	</block>
	<block n="5">
		<token n="грг" u="181,21." witness="#aka">геѡргеи</token>
		<token n="грг" u="181,21." witness="#bych">Георги,</token>
		<token n="грг" u="181,21." witness="#ipa">геѡргии.</token>
		<token n="грг" u="181,21." witness="#kom">георгии</token>
		<token n="грг" u="181,21." witness="#lav">геѡрги</token>
		<token n="грг" u="181,21." witness="#lem">Георгии,</token>
		<token n="грг" u="181,21." witness="#likh">Георги,</token>
		<token n="грг" u="181,21." witness="#nak">георгии</token>
		<token n="" u="181,21." witness="#rad"/>
		<token n="грг" u="181,21." witness="#shakh">Георгии,</token>
		<token n="грг" u="181,21." witness="#tol">георгии</token>
		<token n="грг" u="181,21." witness="#xle">георгїи.</token>
	</block>
	<block n="6">
		<token n="и" u="181,21." witness="#aka">и</token>
		<token n="" u="181,21." witness="#bych"/>
		<token n="" u="181,21." witness="#ipa"/>
		<token n="и" u="181,21." witness="#kom">и</token>
		<token n="" u="181,21." witness="#lav"/>
		<token n="" u="181,21." witness="#lem"/>
		<token n="" u="181,21." witness="#likh"/>
		<token n="и" u="181,21." witness="#nak">и</token>
		<token n="" u="181,21." witness="#rad"/>
		<token n="" u="181,21." witness="#shakh"/>
		<token n="и" u="181,21." witness="#tol">и</token>
		<token n="" u="181,21." witness="#xle"><hi rend="sup">с</hi></token>
	</block>
	<block n="7">
		<token n="епс" u="181,21." witness="#aka">епп<hi rend="sup">с</hi>ъ</token>
		<token n="епск" u="181,21." witness="#bych">епископъ</token>
		<token n="епс" u="181,21." witness="#ipa">епп<hi rend="sup">с</hi>ъ</token>
		<token n="епск" u="181,21." witness="#kom">епископи</token>
		<token n="епс" u="181,21." witness="#lav">епп<hi rend="sup">с</hi>ъ.</token>
		<token n="епск" u="181,21." witness="#lem">епископъ</token>
		<token n="епск" u="181,21." witness="#likh">епископъ</token>
		<token n="епск" u="181,21." witness="#nak">епископи</token>
		<token n="епс" u="181,21." witness="#rad">епп<hi rend="sup">с</hi>ъ</token>
		<token n="епск" u="181,21." witness="#shakh">епископъ</token>
		<token n="епск" u="181,21." witness="#tol">епископи</token>
		<token n="епкс" u="181,21." witness="#xle">епк<hi rend="sup">с</hi>пъ</token>
	</block>
	<block n="8">
		<token n="птр" u="181,21." witness="#aka">петръ</token>
		<token n="птр" u="181,21." witness="#bych">Петръ</token>
		<token n="птр" u="181,21." witness="#ipa"><milestone n="start" unit="sic"/>петръ<milestone n="end" unit="sic"/></token>
		<token n="птр" u="181,21." witness="#kom">петръ</token>
		<token n="птр" u="181,21." witness="#lav">петръ</token>
		<token n="птр" u="181,21." witness="#lem">Петръ</token>
		<token n="птр" u="181,21." witness="#likh">Петръ</token>
		<token n="птр" u="181,21." witness="#nak">петръ</token>
		<token n="птр" u="181,21." witness="#rad">петръ.</token>
		<token n="птр" u="181,21." witness="#shakh">Петръ</token>
		<token n="птр" u="181,21." witness="#tol">петръ</token>
		<token n="птр" u="181,21." witness="#xle">петръ,</token>
	</block>
	<block n="9">
		<token n="прсл" u="181,21." witness="#aka">переꙗ<lb/>славьскыи.</token>
		<token n="прсл" u="181,21." witness="#bych">Переяславьскый,</token>
		<token n="прсл" u="181,21." witness="#ipa">переꙗславьскыи.</token>
		<token n="прсл" u="181,21." witness="#kom">переꙗславьскыи</token>
		<token n="прсл" u="181,21." witness="#lav">переꙗ<milestone n="start" unit="sic"/>сла<milestone n="end" unit="sic"/><lb/>вьскыи. <pb n="61b"/></token>
		<token n="прсл" u="181,21." witness="#lem">Переяславьскыи,</token>
		<token n="прсл" u="181,21." witness="#likh">Переяславьскый,</token>
		<token n="прсл" u="181,21." witness="#nak">переꙗславьскы</token>
		<token n="прсл" u="181,21." witness="#rad">переꙗславь<lb/>ски.</token>
		<token n="прсл" u="181,21." witness="#shakh">Переяславьскыи,</token>
		<token n="прсл" u="181,21." witness="#tol">переꙗславскы</token>
		<token n="прсл" u="181,21." witness="#xle">пе<lb/>реѧславскыи.</token>
	</block>
</witnesses>