{"witnesses": [{"tokens": [{"u": "279,23", "t": "наша,", "n": "нш00"}, {"u": "279,23", "t": "и", "n": "и000"}, {"u": "279,23", "t": "съкруши", "n": "скрш"}, {"u": "279,23", "t": "главы", "n": "глв0"}, {"u": "279,23", "t": "змиевыя,", "n": "змв0"}, {"u": "279,23", "t": "и", "n": "и000"}, {"u": "279,23", "t": "далъ", "n": "дл00"}, {"u": "279,23", "t": "есть", "n": "ест0"}], "id": "#lem"}, {"tokens": [{"u": "279,23", "t": "наша·", "n": "нш00"}, {"u": "279,23", "t": "и", "n": "и000"}, {"u": "279,23", "t": "скру<lb/>ши", "n": "скрш"}, {"u": "279,23", "t": "главы", "n": "глв0"}, {"u": "279,23", "t": "змиевыꙗ·", "n": "змв0"}, {"u": "279,23", "t": "и", "n": "и000"}, {"u": "279,23", "t": "да<lb/>лъ", "n": "дл00"}, {"u": "279,23", "t": "ѥси", "n": "ес00"}], "id": "#lav"}, {"tokens": [{"u": "279,23", "t": "наша· <lb/>", "n": "нш00"}, {"u": "279,23", "t": "и", "n": "и000"}, {"u": "279,23", "t": "сокрѹши", "n": "скрш"}, {"u": "279,23", "t": "главы", "n": "глв0"}, {"u": "279,23", "t": "змиевы·", "n": "змв0"}, {"u": "279,23", "t": "да<hi rend=\"sup\">л</hi>", "n": "дл00"}, {"u": "279,23", "t": "е<hi rend=\"sup\">с</hi>", "n": "ес00"}], "id": "#rad"}, {"tokens": [{"u": "279,23", "t": "наша·", "n": "нш00"}, {"u": "279,23", "t": "и", "n": "и000"}, {"u": "279,23", "t": "съкрѹши", "n": "скрш"}, {"u": "279,23", "t": "главы·̏ <lb/>", "n": "глв̏"}, {"u": "279,23", "t": "змиевы·̏·", "n": "змв̏"}, {"u": "279,23", "t": "далъ", "n": "дл00"}, {"u": "279,23", "t": "есть", "n": "ест0"}], "id": "#aka"}, {"tokens": [{"u": "279,23", "t": "наша·", "n": "нш00"}, {"u": "279,23", "t": "и", "n": "и000"}, {"u": "279,23", "t": "скруши <lb/>", "n": "скрш"}, {"u": "279,23", "t": "главы", "n": "глв0"}, {"u": "279,23", "t": "змѣевыꙗ·", "n": "змв0"}, {"u": "279,23", "t": "и", "n": "и000"}, {"u": "279,23", "t": "далъ", "n": "дл00"}, {"u": "279,23", "t": "есть <lb/>", "n": "ест0"}], "id": "#ipa"}, {"tokens": [{"u": "279,23", "t": "наша.", "n": "нш00"}, {"u": "279,23", "t": "и", "n": "и000"}, {"u": "279,23", "t": "съкроуши", "n": "скрш"}, {"u": "279,23", "t": "главы", "n": "глв0"}, {"u": "279,23", "t": "ѕмїевыа.", "n": "змв0"}, {"u": "279,23", "t": "и", "n": "и000"}, {"u": "279,23", "t": "далъ", "n": "дл00"}, {"u": "279,23", "t": "е<hi rend=\"sup\">с</hi>", "n": "ес00"}], "id": "#xle"}, {"tokens": [{"u": "279,23", "t": "наша,", "n": "нш00"}, {"u": "279,23", "t": "и", "n": "и000"}, {"u": "279,23", "t": "скруши", "n": "скрш"}, {"u": "279,23", "t": "главы", "n": "глв0"}, {"u": "279,23", "t": "змиевыя,", "n": "змв0"}, {"u": "279,23", "t": "и", "n": "и000"}, {"u": "279,23", "t": "далъ", "n": "дл00"}, {"u": "279,23", "t": "еси", "n": "ес00"}], "id": "#bych"}, {"tokens": [{"u": "279,23", "t": "наша,", "n": "нш00"}, {"u": "279,23", "t": "и", "n": "и000"}, {"u": "279,23", "t": "съкруши", "n": "скрш"}, {"u": "279,23", "t": "главы", "n": "глв0"}, {"u": "279,23", "t": "змиевыя,", "n": "змв0"}, {"u": "279,23", "t": "и", "n": "и000"}, {"u": "279,23", "t": "далъ", "n": "дл00"}, {"u": "279,23", "t": "еси", "n": "ес00"}], "id": "#shakh"}, {"tokens": [{"u": "279,23", "t": "наша,", "n": "нш00"}, {"u": "279,23", "t": "и", "n": "и000"}, {"u": "279,23", "t": "“скруши", "n": "скрш"}, {"u": "279,23", "t": "главы", "n": "глв0"}, {"u": "279,23", "t": "змиевыя,", "n": "змв0"}, {"u": "279,23", "t": "и", "n": "и000"}, {"u": "279,23", "t": "далъ", "n": "дл00"}, {"u": "279,23", "t": "еси", "n": "ес00"}], "id": "#likh"}]}