{"witnesses": [{"tokens": [{"u": "3,12", "t": "Куфирана,", "n": "кфрн"}, {"u": "3,12", "t": "Закунфа,", "n": "зкнф"}, {"u": "3,12", "t": "Кефалиния,", "n": "кфлн"}, {"u": "3,12", "t": "Ифакину,", "n": "ифкн"}], "id": "#lem"}, {"tokens": [{"u": "3,12", "t": "кофирана", "n": "кфрн"}, {"u": "3,12", "t": "вакунофа.", "n": "вкнф"}, {"u": "3,12", "t": "кефали<milestone n=\"start\" unit=\"sic\"/>ньꙗ<milestone n=\"end\" unit=\"sic\"/>. <lb/>", "n": "кфлн"}, {"u": "3,12", "t": "ифакину.", "n": "ифкн"}], "id": "#lav"}, {"tokens": [{"u": "3,12", "t": "сефирана", "n": "сфрн"}, {"u": "3,12", "t": "вакунфа", "n": "вкнф"}, {"u": "3,12", "t": "кефалиниа", "n": "кфлн"}, {"u": "3,12", "t": "ефакину", "n": "ефкн"}], "id": "#tro"}, {"tokens": [{"u": "3,12", "t": "коуфирана <lb/>", "n": "кфрн"}, {"u": "3,12", "t": "закоунфа", "n": "зкнф"}, {"u": "3,12", "t": "кефалиниꙗ", "n": "кфлн"}, {"u": "3,12", "t": "ифакинѹ", "n": "ифкн"}], "id": "#rad"}, {"tokens": [{"u": "3,12", "t": "кѹфирина.", "n": "кфрн"}, {"u": "3,12", "t": "закѹнфа <lb/>", "n": "зкнф"}, {"u": "3,12", "t": "кефалинїа.", "n": "кфлн"}, {"u": "3,12", "t": "ифакинѹ.", "n": "ифкн"}], "id": "#aka"}, {"tokens": [{"u": "3,12", "t": "куфирана.", "n": "кфрн"}, {"u": "3,12", "t": "заку<lb/>ньфа.", "n": "зкнф"}, {"u": "3,12", "t": "кефалиниꙗ.", "n": "кфлн"}, {"u": "3,12", "t": "ифаки<lb/>ну.", "n": "ифкн"}], "id": "#ipa"}, {"tokens": [{"u": "3,12", "t": "кифѵрана.", "n": "кфрн"}, {"u": "3,12", "t": "закоу<hi rend=\"sup\">н</hi>фа.", "n": "зкнф"}, {"u": "3,12", "t": "кефа<lb/>линїа.", "n": "кфлн"}, {"u": "3,12", "t": "ифаникоу.", "n": "ифнк"}, {"u": "3,12", "t": "и", "n": "и000"}], "id": "#xle"}, {"tokens": [{"u": "3,12", "t": "Кофирана,", "n": "кфрн"}, {"u": "3,12", "t": "Закунфа,", "n": "зкнф"}, {"u": "3,12", "t": "Кефалинья,", "n": "кфлн"}, {"u": "3,12", "t": "Ифакину,", "n": "ифкн"}], "id": "#bych"}, {"tokens": [{"u": "3,12", "t": "Куфирана,", "n": "кфрн"}, {"u": "3,12", "t": "Закуньфа,", "n": "зкнф"}, {"u": "3,12", "t": "Кефалиния,", "n": "кфлн"}, {"u": "3,12", "t": "Ифакину,", "n": "ифкн"}], "id": "#shakh"}, {"tokens": [{"u": "3,12", "t": "Кофирана,", "n": "кфрн"}, {"u": "3,12", "t": "Закунфа,", "n": "зкнф"}, {"u": "3,12", "t": "Кефалинъя,", "n": "кфлн"}, {"u": "3,12", "t": "Ифакину,", "n": "ифкн"}], "id": "#likh"}], "tokenComparator": {"distance": 2, "type": "levenshtein"}}