{"witnesses": [{"tokens": [{"u": "19,22", "t": "ты", "n": "т000"}, {"u": "19,22", "t": "Варягы", "n": "врг0"}, {"u": "19,22", "t": "Русь,", "n": "рс00"}, {"u": "19,22", "t": "яко", "n": "ѧк00"}, {"u": "19,22", "t": "се", "n": "с000"}, {"u": "19,22", "t": "друзии", "n": "дрз0"}, {"u": "19,22", "t": "зовуть", "n": "звт0"}, {"u": "19,22", "t": "ся", "n": "с000"}], "id": "#lem"}, {"tokens": [{"u": "19,22", "t": "и.", "n": "и000"}, {"u": "19,22", "t": "варѧзи", "n": "врз0"}, {"u": "19,22", "t": "суть.", "n": "ст00"}, {"u": "19,22", "t": "ꙗко", "n": "ѧк00"}, {"u": "19,22", "t": "се", "n": "с000"}, {"u": "19,22", "t": "друзии", "n": "дрз0"}, {"u": "19,22", "t": "зо<lb/>вутсѧ", "n": "звтс"}], "id": "#lav"}, {"tokens": [{"u": "19,22", "t": "ти", "n": "т000"}, {"u": "19,22", "t": "варязи", "n": "врз0"}, {"u": "19,22", "t": "русью", "n": "рс00"}, {"u": "19,22", "t": "яко", "n": "ѧк00"}, {"u": "19,22", "t": "сии", "n": "с000"}, {"u": "19,22", "t": "друзии", "n": "дрз0"}, {"u": "19,22", "t": "зовуться", "n": "звтс"}], "id": "#tro"}, {"tokens": [{"u": "19,22", "t": "варѧзи", "n": "врз0"}, {"u": "19,22", "t": "роу<hi rend=\"sup\">с</hi>", "n": "рс00"}, {"u": "19,22", "t": "ꙗко", "n": "ѧк00"}, {"u": "19,22", "t": "се", "n": "с000"}, {"u": "19,22", "t": "дроузии", "n": "дрз0"}, {"u": "19,22", "t": "зовоуть<hi rend=\"sup\">с</hi>", "n": "звтс"}], "id": "#rad"}, {"tokens": [{"u": "19,22", "t": "варѧзї", "n": "врз0"}, {"u": "19,22", "t": "рѹ<hi rend=\"sup\">с</hi>", "n": "рс00"}, {"u": "19,22", "t": "ꙗко", "n": "ѧк00"}, {"u": "19,22", "t": "се", "n": "с000"}, {"u": "19,22", "t": "дрѹзии", "n": "дрз0"}, {"u": "19,22", "t": "зовѹть<hi rend=\"sup\">с</hi>", "n": "звтс"}], "id": "#aka"}, {"tokens": [{"u": "19,22", "t": "ты", "n": "т000"}, {"u": "19,22", "t": "вар<hi rend=\"sup\">ѧ</hi>гы", "n": "врг0"}, {"u": "19,22", "t": "русь.", "n": "рс00"}, {"u": "19,22", "t": "ꙗко", "n": "ѧк00"}, {"u": "19,22", "t": "се", "n": "с000"}, {"u": "19,22", "t": "друзии <lb/>", "n": "дрз0"}, {"u": "19,22", "t": "зовутсѧ", "n": "звтс"}], "id": "#ipa"}, {"tokens": [{"u": "19,22", "t": "ты<hi rend=\"sup\">и</hi>", "n": "т000"}, {"u": "19,22", "t": "варѧгы", "n": "врг0"}, {"u": "19,22", "t": "роу<hi rend=\"sup\">с</hi>.", "n": "рс00"}, {"u": "19,22", "t": "яко", "n": "ѧк00"}, {"u": "19,22", "t": "<milestone n=\"start\" unit=\"sic\"/>се<milestone n=\"end\" unit=\"sic\"/>", "n": "с000"}, {"u": "19,22", "t": "дрѹѕїи", "n": "дрз0"}, {"u": "19,22", "t": "зовоутсѧ", "n": "звтс"}], "id": "#xle"}, {"tokens": [{"u": "19,22", "t": "Варязи", "n": "врз0"}, {"u": "19,22", "t": "Русь,", "n": "рс00"}, {"u": "19,22", "t": "яко", "n": "ѧк00"}, {"u": "19,22", "t": "се", "n": "с000"}, {"u": "19,22", "t": "друзии", "n": "дрз0"}, {"u": "19,22", "t": "зовутся", "n": "звтс"}], "id": "#bych"}, {"tokens": [{"u": "19,22", "t": "ти", "n": "т000"}, {"u": "19,22", "t": "Варязи", "n": "врз0"}, {"u": "19,22", "t": "Русь,", "n": "рс00"}, {"u": "19,22", "t": "яко", "n": "ѧк00"}, {"u": "19,22", "t": "се", "n": "с000"}, {"u": "19,22", "t": "друзии", "n": "дрз0"}, {"u": "19,22", "t": "зовуться", "n": "звтс"}], "id": "#shakh"}, {"tokens": [{"u": "19,22", "t": "тьи", "n": "т000"}, {"u": "19,22", "t": "варязи", "n": "врз0"}, {"u": "19,22", "t": "русь,", "n": "рс00"}, {"u": "19,22", "t": "яко", "n": "ѧк00"}, {"u": "19,22", "t": "се", "n": "с000"}, {"u": "19,22", "t": "друзии", "n": "дрз0"}, {"u": "19,22", "t": "зовутся", "n": "звтс"}], "id": "#likh"}], "tokenComparator": {"distance": 1, "type": "levenshtein"}}