{"witnesses": [{"tokens": [{"u": "88,6.", "t": "сотона", "n": "стн"}, {"u": "88,6.", "t": "же,", "n": "же"}, {"u": "88,6.", "t": "грѣшивъ", "n": "гршв"}, {"u": "88,6.", "t": "помысла", "n": "пмсл"}, {"u": "88,6.", "t": "своего,", "n": "свг"}, {"u": "88,6.", "t": "и", "n": "и"}], "id": "#lem"}, {"tokens": [{"u": "88,6.", "t": "сотона", "n": "стн"}, {"u": "88,6.", "t": "же", "n": "же"}, {"u": "88,6.", "t": "грѣшивъ", "n": "гршв"}, {"u": "88,6.", "t": "помысла", "n": "пмсл"}, {"u": "88,6.", "t": "своего.", "n": "свг"}, {"u": "88,6.", "t": "и <lb/>", "n": "и"}], "id": "#lav"}, {"tokens": [{"u": "88,6.", "t": "сотона<hi rend=\"sup\">ж</hi>", "n": "стнж"}, {"u": "88,6.", "t": "грешивъ", "n": "гршв"}, {"u": "88,6.", "t": "помысла", "n": "пмсл"}, {"u": "88,6.", "t": "свое<hi rend=\"sup\">г</hi>.", "n": "свг"}, {"u": "88,6.", "t": "и", "n": "и"}], "id": "#rad"}, {"tokens": [{"u": "88,6.", "t": "сотона", "n": "стн"}, {"u": "88,6.", "t": "же", "n": "же"}, {"u": "88,6.", "t": "грешивь", "n": "гршв"}, {"u": "88,6.", "t": "помысла", "n": "пмсл"}, {"u": "88,6.", "t": "своего. <lb/>", "n": "свг"}, {"u": "88,6.", "t": "и", "n": "и"}], "id": "#aka"}, {"tokens": [{"u": "88,6.", "t": "с<milestone n=\"start\" unit=\"sic\"/>а<milestone n=\"end\" unit=\"sic\"/>т<milestone n=\"start\" unit=\"sic\"/>а<milestone n=\"end\" unit=\"sic\"/><lb/>на", "n": "стн"}, {"u": "88,6.", "t": "же", "n": "же"}, {"u": "88,6.", "t": "грѣшивъ", "n": "гршв"}, {"u": "88,6.", "t": "помысла <lb/>", "n": "пмсл"}, {"u": "88,6.", "t": "своего.", "n": "свг"}, {"u": "88,6.", "t": "и", "n": "и"}], "id": "#ipa"}, {"tokens": [{"u": "88,6.", "t": "сатана<hi rend=\"sup\">ж</hi>", "n": "стнж"}, {"u": "88,6.", "t": "грѣшивь", "n": "гршв"}, {"u": "88,6.", "t": "помысла <lb/>", "n": "пмсл"}, {"u": "88,6.", "t": "своего.", "n": "свг"}, {"u": "88,6.", "t": "и", "n": "и"}], "id": "#xle"}, {"tokens": [{"u": "88,6.", "t": "он", "n": "он"}, {"u": "88,6.", "t": "же", "n": "же"}, {"u": "88,6.", "t": "погрѣши", "n": "пгрш"}, {"u": "88,6.", "t": "помысла", "n": "пмсл"}, {"u": "88,6.", "t": "своего", "n": "свг"}, {"u": "88,6.", "t": "и", "n": "и"}], "id": "#kom"}, {"tokens": [{"u": "88,6.", "t": "сотона", "n": "стн"}, {"u": "88,6.", "t": "же,", "n": "же"}, {"u": "88,6.", "t": "грѣшивъ", "n": "гршв"}, {"u": "88,6.", "t": "помысла", "n": "пмсл"}, {"u": "88,6.", "t": "своего", "n": "свг"}, {"u": "88,6.", "t": "и", "n": "и"}], "id": "#bych"}, {"tokens": [{"u": "88,6.", "t": "сотона", "n": "стн"}, {"u": "88,6.", "t": "же,", "n": "же"}, {"u": "88,6.", "t": "грѣшивъ", "n": "гршв"}, {"u": "88,6.", "t": "помысла", "n": "пмсл"}, {"u": "88,6.", "t": "своего,", "n": "свг"}, {"u": "88,6.", "t": "и", "n": "и"}], "id": "#shakh"}, {"tokens": [{"u": "88,6.", "t": "Сотона", "n": "стн"}, {"u": "88,6.", "t": "же,", "n": "же"}, {"u": "88,6.", "t": "грѣшивъ", "n": "гршв"}, {"u": "88,6.", "t": "помысла", "n": "пмсл"}, {"u": "88,6.", "t": "своего", "n": "свг"}, {"u": "88,6.", "t": "и", "n": "и"}], "id": "#likh"}]}