{"witnesses": [{"tokens": [{"u": "190,17.", "t": "вьржаше", "n": "вржш"}, {"u": "190,17.", "t": "на", "n": "на"}, {"u": "190,17.", "t": "кого", "n": "кг"}, {"u": "190,17.", "t": "любо.", "n": "лб"}, {"u": "190,17.", "t": "Аще", "n": "ащ"}, {"u": "190,17.", "t": "прильняше", "n": "прлн"}, {"u": "190,17.", "t": "кому", "n": "км"}], "id": "#lem"}, {"tokens": [{"u": "190,17.", "t": "вержаше", "n": "вржш"}, {"u": "190,17.", "t": "на <lb/>", "n": "на"}, {"u": "190,17.", "t": "кого", "n": "кг"}, {"u": "190,17.", "t": "любо.", "n": "лб"}, {"u": "190,17.", "t": "аще", "n": "ащ"}, {"u": "190,17.", "t": "прилнѧше", "n": "прлн"}, {"u": "190,17.", "t": "ко<lb/>му", "n": "км"}], "id": "#lav"}, {"tokens": [{"u": "190,17.", "t": "верже", "n": "врж"}, {"u": "190,17.", "t": "на", "n": "на"}, {"u": "190,17.", "t": "кого", "n": "кг"}, {"u": "190,17.", "t": "либо.", "n": "лб"}, {"u": "190,17.", "t": "и", "n": "и"}, {"u": "190,17.", "t": "аще", "n": "ащ"}, {"u": "190,17.", "t": "прилне", "n": "прлн"}, {"u": "190,17.", "t": "к", "n": "к"}, {"u": "190,17.", "t": "комѹ <lb/>", "n": "км"}], "id": "#rad"}, {"tokens": [{"u": "190,17.", "t": "верже", "n": "врж"}, {"u": "190,17.", "t": "на", "n": "на"}, {"u": "190,17.", "t": "кого", "n": "кг"}, {"u": "190,17.", "t": "либо", "n": "лб"}, {"u": "190,17.", "t": "и", "n": "и"}, {"u": "190,17.", "t": "аще", "n": "ащ"}, {"u": "190,17.", "t": "прилне", "n": "прлн"}, {"u": "190,17.", "t": "кь", "n": "кь"}, {"u": "190,17.", "t": "комѹ.", "n": "км"}], "id": "#aka"}, {"tokens": [{"u": "190,17.", "t": "вѣржаше", "n": "вржш"}, {"u": "190,17.", "t": "на", "n": "на"}, {"u": "190,17.", "t": "кого", "n": "кг"}, {"u": "190,17.", "t": "любо.", "n": "лб"}, {"u": "190,17.", "t": "аще", "n": "ащ"}, {"u": "190,17.", "t": "прилпѧше", "n": "прлп"}, {"u": "190,17.", "t": "кьму <pb n=\"70c\"/>", "n": "км"}], "id": "#ipa"}, {"tokens": [{"u": "190,17.", "t": "вержаше", "n": "вржш"}, {"u": "190,17.", "t": "на", "n": "на"}, {"u": "190,17.", "t": "кого", "n": "кг"}, {"u": "190,17.", "t": "любо.", "n": "лб"}, {"u": "190,17.", "t": "и", "n": "и"}, {"u": "190,17.", "t": "аще", "n": "ащ"}, {"u": "190,17.", "t": "при<lb/>липлѧше", "n": "прлп"}, {"u": "190,17.", "t": "къмоу", "n": "км"}], "id": "#xle"}, {"tokens": [{"u": "190,17.", "t": "вержаше", "n": "вржш"}, {"u": "190,17.", "t": "на", "n": "на"}, {"u": "190,17.", "t": "кого", "n": "кг"}, {"u": "190,17.", "t": "любо:", "n": "лб"}, {"u": "190,17.", "t": "аще", "n": "ащ"}, {"u": "190,17.", "t": "прилняше", "n": "прлн"}, {"u": "190,17.", "t": "кому", "n": "км"}], "id": "#bych"}, {"tokens": [{"u": "190,17.", "t": "вьржаше", "n": "вржш"}, {"u": "190,17.", "t": "на", "n": "на"}, {"u": "190,17.", "t": "кого", "n": "кг"}, {"u": "190,17.", "t": "любо;", "n": "лб"}, {"u": "190,17.", "t": "аще", "n": "ащ"}, {"u": "190,17.", "t": "прильняше", "n": "прлн"}, {"u": "190,17.", "t": "кому", "n": "км"}], "id": "#shakh"}, {"tokens": [{"u": "190,17.", "t": "вержаше", "n": "вржш"}, {"u": "190,17.", "t": "на", "n": "на"}, {"u": "190,17.", "t": "кого", "n": "кг"}, {"u": "190,17.", "t": "любо:", "n": "лб"}, {"u": "190,17.", "t": "аще", "n": "ащ"}, {"u": "190,17.", "t": "прилняше", "n": "прлн"}, {"u": "190,17.", "t": "кому", "n": "км"}], "id": "#likh"}]}