<?xml version="1.0" ?>
<witnesses>
	<block>
		<token n="зб00" u="" witness="#aka">ѕлобы</token>
		<token n="зб00" u="" witness="#bych">злобы</token>
		<token n="зб00" u="" witness="#ipa">злобы</token>
		<token n="зб00" u="" witness="#lav">злобы</token>
		<token n="зб00" u="" witness="#likh">злобы</token>
		<token n="зб00" u="" witness="#rad">злобы</token>
		<token n="зб00" u="" witness="#shakh">зълобы</token>
	</block>
	<block>
		<token n="трщ0" u="" witness="#aka">творѧще.</token>
		<token n="трящ" u="" witness="#bych">творяще,</token>
		<token n="трщ0" u="" witness="#ipa">творѧще.</token>
		<token n="трщ0" u="" witness="#lav">творѧщ<hi rend="sup">е</hi><lb/></token>
		<token n="трящ" u="" witness="#likh">творяще,</token>
		<token n="трщ0" u="" witness="#rad">творѧще.</token>
		<token n="трящ" u="" witness="#shakh">творяще,</token>
	</block>
	<block>
		<token n="срх0" u="" witness="#aka">стра<milestone n="start" place="margin" unit="add"/>ха<milestone n="end" unit="add"/></token>
		<token n="срх0" u="" witness="#bych">страха</token>
		<token n="срх0" u="" witness="#ipa">стра<lb/>ха</token>
		<token n="срх0" u="" witness="#lav">страха</token>
		<token n="срх0" u="" witness="#likh">страха</token>
		<token n="срх0" u="" witness="#rad">страха</token>
		<token n="срх0" u="" witness="#shakh">страха</token>
	</block>
	<block>
		<token n="рд00" u="" witness="#aka">радї</token>
		<token n="рд00" u="" witness="#bych">ради</token>
		<token n="р000" u="" witness="#ipa">р<hi rend="sup">д</hi>а</token>
		<token n="рд00" u="" witness="#lav">ради</token>
		<token n="рд00" u="" witness="#likh">ради</token>
		<token n="р000" u="" witness="#rad">р<hi rend="sup">д</hi>а</token>
		<token n="рд00" u="" witness="#shakh">ради</token>
	</block>
	<block>
		<token n="мг00" u="" witness="#aka">многа.</token>
		<token n="мг00" u="" witness="#bych">многа</token>
		<token n="мг00" u="" witness="#ipa">многа.</token>
		<token n="мг00" u="" witness="#lav">многа.</token>
		<token n="мг00" u="" witness="#likh">многа</token>
		<token n="мг00" u="" witness="#rad">многа.</token>
		<token n="мг00" u="" witness="#shakh">мънога</token>
	</block>
	<block>
		<token n="" u="" witness="#aka"></token>
		<token n="" u="" witness="#bych"></token>
		<token n="" u="" witness="#ipa"></token>
		<token n="" u="" witness="#lav"></token>
		<token n="" u="" witness="#likh"></token>
		<token n="" u="" witness="#rad"></token>
		<token n="и000" u="" witness="#shakh">и</token>
	</block>
	<block>
		<token n="" u="" witness="#aka"></token>
		<token n="бжя0" u="" witness="#bych">Божия</token>
		<token n="" u="" witness="#ipa"></token>
		<token n="" u="" witness="#lav"></token>
		<token n="бжя0" u="" witness="#likh">божия</token>
		<token n="" u="" witness="#rad"></token>
		<token n="бжя0" u="" witness="#shakh">Бо(жи)я</token>
	</block>
</witnesses>

