<?xml version="1.0" ?>
<witnesses>
	<block>
		<token n="однX" u="82,26" witness="#aka">ѡдинъ.</token>
		<token n="еднX" u="82,26" witness="#bych">единъ,</token>
		<token n="естX" u="82,26" witness="#ipa">есть. <lb/></token>
		<token n="еднX" u="82,26" witness="#kom">единъ</token>
		<token n="еднX" u="82,26" witness="#lav">единъ</token>
		<token n="еднX" u="82,26" witness="#lem">единъ,</token>
		<token n="еднX" u="82,26" witness="#likh">единъ,</token>
		<token n="еднX" u="82,26" witness="#nak">единъ</token>
		<token n="еднX" u="82,26" witness="#rad">единъ.</token>
		<token n="еднX" u="82,26" witness="#shakh">единъ,</token>
		<token n="еднX" u="82,26" witness="#tol">единъ</token>
		<token n="есXX" u="82,26" witness="#xle">е<hi rend="sup">с</hi>.</token>
	</block>
	<block>
		<token n="емжX" u="82,26" witness="#aka">емѹже</token>
		<token n="емжX" u="82,26" witness="#bych">емуже</token>
		<token n="емжX" u="82,26" witness="#ipa">емуже</token>
		<token n="емжX" u="82,26" witness="#kom">емуже</token>
		<token n="емжX" u="82,26" witness="#lav">ему<lb/>же</token>
		<token n="емжX" u="82,26" witness="#lem">емуже</token>
		<token n="емXX" u="82,26" witness="#likh">ему</token>
		<token n="емжX" u="82,26" witness="#nak">емуже</token>
		<token n="емжX" u="82,26" witness="#rad">емоу<hi rend="sup">ж</hi></token>
		<token n="емжX" u="82,26" witness="#shakh">емуже</token>
		<token n="емжX" u="82,26" witness="#tol">емуже</token>
		<token n="емжX" u="82,26" witness="#xle">емоуже</token>
	</block>
	<block>
		<token n="" u="" witness="#aka"></token>
		<token n="" u="" witness="#bych"></token>
		<token n="" u="" witness="#ipa"></token>
		<token n="" u="" witness="#kom"></token>
		<token n="" u="" witness="#lav"></token>
		<token n="" u="" witness="#lem"></token>
		<token n="жXXX" u="82,26" witness="#likh">же</token>
		<token n="" u="" witness="#nak"></token>
		<token n="" u="" witness="#rad"></token>
		<token n="" u="" witness="#shakh"></token>
		<token n="" u="" witness="#tol"></token>
		<token n="" u="" witness="#xle"></token>
	</block>
	<block>
		<token n="слжт" u="82,26" witness="#aka">слѹжать</token>
		<token n="слжт" u="82,26" witness="#bych">служать</token>
		<token n="слжт" u="82,26" witness="#ipa">служать</token>
		<token n="слжт" u="82,26" witness="#kom">служать</token>
		<token n="слжт" u="82,26" witness="#lav">служа<hi rend="sup">т</hi></token>
		<token n="слжт" u="82,26" witness="#lem">служать</token>
		<token n="слжт" u="82,26" witness="#likh">служать</token>
		<token n="слжт" u="82,26" witness="#nak">служать</token>
		<token n="слжт" u="82,26" witness="#rad">слѹжать</token>
		<token n="слжт" u="82,26" witness="#shakh">служать</token>
		<token n="слжт" u="82,26" witness="#tol">служать</token>
		<token n="слжт" u="82,26" witness="#xle">слоужа<hi rend="sup">т</hi></token>
	</block>
	<block>
		<token n="грцX" u="82,26" witness="#aka">греци</token>
		<token n="грцX" u="82,26" witness="#bych">Грьци</token>
		<token n="грцX" u="82,26" witness="#ipa">грѣци.</token>
		<token n="грцX" u="82,26" witness="#kom">грѣцѣ</token>
		<token n="грцX" u="82,26" witness="#lav">грьци.</token>
		<token n="грцX" u="82,26" witness="#lem">Грьци,</token>
		<token n="грцX" u="82,26" witness="#likh">грьци</token>
		<token n="грцX" u="82,26" witness="#nak">греци</token>
		<token n="грцX" u="82,26" witness="#rad">греци</token>
		<token n="грцX" u="82,26" witness="#shakh">Грьци,</token>
		<token n="грцX" u="82,26" witness="#tol">греци</token>
		<token n="грцX" u="82,26" witness="#xle">гре<lb/>ци</token>
	</block>
	<block>
		<token n="иXXX" u="82,26" witness="#aka">и</token>
		<token n="иXXX" u="82,26" witness="#bych">и</token>
		<token n="иXXX" u="82,26" witness="#ipa">и <lb/></token>
		<token n="иXXX" u="82,26" witness="#kom">и</token>
		<token n="иXXX" u="82,26" witness="#lav">и</token>
		<token n="иXXX" u="82,26" witness="#lem">и</token>
		<token n="иXXX" u="82,26" witness="#likh">и</token>
		<token n="иXXX" u="82,26" witness="#nak">и</token>
		<token n="иXXX" u="82,26" witness="#rad">и</token>
		<token n="иXXX" u="82,26" witness="#shakh">и</token>
		<token n="иXXX" u="82,26" witness="#tol">и</token>
		<token n="иXXX" u="82,26" witness="#xle">и</token>
	</block>
	<block>
		<token n="пклн" u="82,26" witness="#aka">покланѧють<lb/>сѧ.</token>
		<token n="клнт" u="82,26" witness="#bych">кланяются,</token>
		<token n="клнт" u="82,26" witness="#ipa">кланѧютсѧ.</token>
		<token n="клнт" u="82,26" witness="#kom">кланꙗютсꙗ</token>
		<token n="клнт" u="82,26" witness="#lav">кланѧютсѧ</token>
		<token n="клнт" u="82,26" witness="#lem">кланяють</token>
		<token n="клнт" u="82,26" witness="#likh">кланяются,</token>
		<token n="клнт" u="82,26" witness="#nak">кланꙗютсꙗ</token>
		<token n="пклн" u="82,26" witness="#rad">покла<lb/>нѧютсѧ.</token>
		<token n="клнт" u="82,26" witness="#shakh">кланяються,</token>
		<token n="клнт" u="82,26" witness="#tol">кланꙗютсꙗ</token>
		<token n="пклн" u="82,26" witness="#xle">поклонѧютсѧ.</token>
	</block>
	<block>
		<token n="" u="" witness="#aka"></token>
		<token n="" u="" witness="#bych"></token>
		<token n="" u="" witness="#ipa"></token>
		<token n="" u="" witness="#kom"></token>
		<token n="" u="" witness="#lav"></token>
		<token n="сXXX" u="82,26" witness="#lem">ся,</token>
		<token n="" u="" witness="#likh"></token>
		<token n="" u="" witness="#nak"></token>
		<token n="" u="" witness="#rad"></token>
		<token n="" u="" witness="#shakh"></token>
		<token n="" u="" witness="#tol"></token>
		<token n="" u="" witness="#xle"></token>
	</block>
	<block>
		<token n="ижXX" u="82,26" witness="#aka">иже</token>
		<token n="ижXX" u="82,26" witness="#bych">иже</token>
		<token n="ижXX" u="82,26" witness="#ipa">иже</token>
		<token n="ижXX" u="82,26" witness="#kom">иже</token>
		<token n="ижXX" u="82,26" witness="#lav">иже</token>
		<token n="ижXX" u="82,26" witness="#lem">иже</token>
		<token n="ижXX" u="82,26" witness="#likh">иже</token>
		<token n="ижXX" u="82,26" witness="#nak">иже</token>
		<token n="ижXX" u="82,26" witness="#rad">иже</token>
		<token n="ижXX" u="82,26" witness="#shakh">иже</token>
		<token n="ижXX" u="82,26" witness="#tol">иже</token>
		<token n="ижXX" u="82,26" witness="#xle">иже</token>
	</block>
</witnesses>

