{"witnesses":["#aka","#bych","#kom","#lav","#lem","#likh","#nak","#rad","#shakh","#tol","#xle"],"table":[[[{"u":"106,1","t":"и","n":"иXXX"}],[{"u":"106,1","t":"и","n":"иXXX"}],[{"u":"106,1","t":"и","n":"иXXX"}],[{"u":"106,1","t":"и","n":"иXXX"}],[{"u":"106,1","t":"и","n":"иXXX"}],[{"u":"106,1","t":"и","n":"иXXX"}],[],[{"u":"106,1","t":"и","n":"иXXX"}],[{"u":"106,1","t":"и","n":"иXXX"}],[],[{"u":"106,1","t":"и","n":"иXXX"}]],[[{"u":"106,1","t":"мѹцѣ","n":"мцXX"}],[{"u":"106,1","t":"муцѣ","n":"мцXX"}],[{"u":"106,1","t":"муцѣ","n":"мцXX"}],[{"u":"106,1","t":"мц҃ѣ","n":"мцXX"}],[{"u":"106,1","t":"муцѣ","n":"мцXX"}],[{"u":"106,1","t":"муцѣ","n":"мцXX"}],[{"u":"106,1","t":"муцѣ","n":"мцXX"}],[{"u":"106,1","t":"моуцѣ","n":"мцXX"}],[{"u":"106,1","t":"муцѣ","n":"мцXX"}],[{"u":"106,1","t":"муцѣ","n":"мцXX"}],[{"u":"106,1","t":"мѫцѣ","n":"мцXX"}]],[[{"u":"106,1","t":"не","n":"нXXX"}],[{"u":"106,1","t":"не","n":"нXXX"}],[{"u":"106,1","t":"не","n":"нXXX"}],[{"u":"106,1","t":"не","n":"нXXX"}],[{"u":"106,1","t":"не","n":"нXXX"}],[{"u":"106,1","t":"не","n":"нXXX"}],[{"u":"106,1","t":"не","n":"нXXX"}],[{"u":"106,1","t":"не","n":"нXXX"}],[{"u":"106,1","t":"не","n":"нXXX"}],[{"u":"106,1","t":"не","n":"нXXX"}],[{"u":"106,1","t":"не","n":"нXXX"}]],[[{"u":"106,1","t":"бѹдетъ","n":"бдтX"}],[{"u":"106,1","t":"будеть","n":"бдтX"}],[{"u":"106,1","t":"будет","n":"бдтX"}],[{"u":"106,1","t":"буде<hi rend=\"sup\">т</hi>","n":"бдтX"}],[{"u":"106,1","t":"будеть","n":"бдтX"}],[{"u":"106,1","t":"будеть","n":"бдтX"}],[{"u":"106,1","t":"будеть","n":"бдтX"}],[{"u":"106,1","t":"боу<hi rend=\"sup\">д</hi>ть","n":"бдтX"}],[{"u":"106,1","t":"будеть","n":"бдтX"}],[{"u":"106,1","t":"будетъ","n":"бдтX"}],[{"u":"106,1","t":"бѫде<hi rend=\"sup\">т</hi>","n":"бдтX"}]],[[{"u":"106,1","t":"конца.","n":"кнцX"}],[{"u":"106,1","t":"конца.","n":"кнцX"}],[{"u":"106,1","t":"конца","n":"кнцX"}],[{"u":"106,1","t":"конца.","n":"кнцX"}],[{"u":"106,1","t":"коньца.","n":"кнцX"}],[{"u":"106,1","t":"конца.","n":"кнцX"}],[{"u":"106,1","t":"коньца","n":"кнцX"}],[{"u":"106,1","t":"конца.","n":"кнцX"}],[{"u":"106,1","t":"коньца.","n":"кнцX"}],[{"u":"106,1","t":"конца","n":"кнцX"}],[{"u":"106,1","t":"конца.","n":"кнцX"}]],[[{"u":"106,1","t":"сице","n":"сцXX"}],[{"u":"106,1","t":"Сица","n":"сцXX"}],[{"u":"106,1","t":"сица","n":"сцXX"}],[{"u":"106,1","t":"сица","n":"сцXX"}],[{"u":"106,1","t":"Сица","n":"сцXX"}],[{"u":"106,1","t":"Сица","n":"сцXX"}],[{"u":"106,1","t":"сицева","n":"сцвX"}],[{"u":"106,1","t":"сице","n":"сцXX"}],[{"u":"106,1","t":"Сица","n":"сцXX"}],[{"u":"106,1","t":"сицева","n":"сцвX"}],[{"u":"106,1","t":"сице","n":"сцXX"}]],[[{"u":"106,1","t":"же","n":"жXXX"}],[{"u":"106,1","t":"же","n":"жXXX"}],[{"u":"106,1","t":"же","n":"жXXX"}],[{"u":"106,1","t":"же","n":"жXXX"}],[{"u":"106,1","t":"же","n":"жXXX"}],[{"u":"106,1","t":"же","n":"жXXX"}],[{"u":"106,1","t":"же","n":"жXXX"}],[{"u":"106,1","t":"же","n":"жXXX"}],[{"u":"106,1","t":"же","n":"жXXX"}],[{"u":"106,1","t":"же","n":"жXXX"}],[{"u":"106,1","t":"же <lb/>","n":"жXXX"}]],[[{"u":"106,1","t":"бѹдетъ","n":"бдтX"}],[{"u":"106,1","t":"будуть <pb n=\"103,17\"/>","n":"бдтX"}],[{"u":"106,1","t":"бысть","n":"бстX"}],[{"u":"106,1","t":"бу<hi rend=\"sup\">д</hi><lb/>ть","n":"бдтX"}],[{"u":"106,1","t":"будуть","n":"бдтX"}],[{"u":"106,1","t":"будуть <pb n=\"73,34\"/>","n":"бдтX"}],[{"u":"106,1","t":"будеть","n":"бдтX"}],[{"u":"106,1","t":"боудоу<hi rend=\"sup\">т</hi><lb/>","n":"бдтX"}],[{"u":"106,1","t":"будуть <pb n=\"133,4\"/>","n":"бдтX"}],[{"u":"106,1","t":"будетъ","n":"бдтX"}],[{"u":"106,1","t":"бѫдоу<hi rend=\"sup\">т</hi>","n":"бдтX"}]]]}