<?xml version="1.0" ?>
<witnesses>
	<block>
		<token n="вXXX" u="155,19" witness="#aka">В</token>
		<token n="вXXX" u="155,19" witness="#bych">В</token>
		<token n="вXXX" u="155,19" witness="#ipa">В</token>
		<token n="вXXX" u="155,19" witness="#lav">В</token>
		<token n="вXXX" u="155,19" witness="#lem">В</token>
		<token n="вXXX" u="155,19" witness="#likh">В</token>
		<token n="вXXX" u="155,19" witness="#rad">В</token>
		<token n="вXXX" u="155,19" witness="#shakh">В</token>
		<token n="вXXX" u="155,19" witness="#xle">В</token>
	</block>
	<block>
		<token n="лтXX" u="155,19" witness="#aka">лѣ<hi rend="sup">т</hi></token>
		<token n="лт҂з" u="155,19" witness="#bych">лѣто 6555.</token>
		<token n="лтXX" u="155,19" witness="#ipa">лѣ<hi rend="sup">т</hi></token>
		<token n="лтXX" u="155,19" witness="#lav">лѣ<hi rend="sup">т</hi></token>
		<token n="лт҂з" u="155,19" witness="#lem">лѣто 6555.</token>
		<token n="лт҂з" u="155,19" witness="#likh">лѣто 6555.</token>
		<token n="лтXX" u="155,19" witness="#rad">лѣ<hi rend="sup">т</hi></token>
		<token n="лт҂з" u="155,19" witness="#shakh">лѣто 6555.</token>
		<token n="лтXX" u="155,19" witness="#xle">лѣ<hi rend="sup">т</hi></token>
	</block>
	<block>
		<token n="҂зXX" u="155,19" witness="#aka">.҂ѕ҃.</token>
		<token n="" u="" witness="#bych"></token>
		<token n="҂зфн" u="155,19" witness="#ipa">.҂ѕ҃.ф҃.н҃е.</token>
		<token n="҂зфн" u="155,19" witness="#lav">.҂ѕ҃.ф҃.н҃е.</token>
		<token n="" u="" witness="#lem"></token>
		<token n="" u="" witness="#likh"></token>
		<token n="҂зXX" u="155,19" witness="#rad">҂ѕ҃</token>
		<token n="" u="" witness="#shakh"></token>
		<token n="҂зфн" u="155,19" witness="#xle">҂ѕ҃.ф҃.н҃е.</token>
	</block>
	<block>
		<token n="нXXX" u="155,19" witness="#aka">н҃е. <lb/></token>
		<token n="" u="" witness="#bych"></token>
		<token n="" u="" witness="#ipa"></token>
		<token n="" u="" witness="#lav"></token>
		<token n="" u="" witness="#lem"></token>
		<token n="" u="" witness="#likh"></token>
		<token n="фнXX" u="155,19" witness="#rad">ф҃.н҃е</token>
		<token n="" u="" witness="#shakh"></token>
		<token n="" u="" witness="#xle"></token>
	</block>
	<block>
		<token n="идXX" u="155,19" witness="#aka">иде</token>
		<token n="" u="" witness="#bych"></token>
		<token n="" u="" witness="#ipa"></token>
		<token n="" u="" witness="#lav"></token>
		<token n="" u="" witness="#lem"></token>
		<token n="" u="" witness="#likh"></token>
		<token n="идXX" u="155,19" witness="#rad">Иде</token>
		<token n="" u="" witness="#shakh"></token>
		<token n="" u="" witness="#xle"></token>
	</block>
	<block>
		<token n="ѧрсл" u="155,19" witness="#aka">ꙗрославъ</token>
		<token n="ѧрсл" u="155,19" witness="#bych">Ярославъ</token>
		<token n="ѧрсл" u="155,19" witness="#ipa">Ярославъ <lb/></token>
		<token n="ѧрсл" u="155,19" witness="#lav">Ярославъ</token>
		<token n="ѧрсл" u="155,19" witness="#lem">Ярославъ</token>
		<token n="ѧрсл" u="155,19" witness="#likh">Ярославъ</token>
		<token n="ѧрсл" u="155,19" witness="#rad">ꙗ<lb/>рославъ</token>
		<token n="ѧрсл" u="155,19" witness="#shakh">Ярославъ</token>
		<token n="ѧрсл" u="155,19" witness="#xle">ярославь</token>
	</block>
	<block>
		<token n="" u="" witness="#aka"></token>
		<token n="идXX" u="155,19" witness="#bych">иде</token>
		<token n="идXX" u="155,19" witness="#ipa">иде</token>
		<token n="идXX" u="155,19" witness="#lav">иде <lb/></token>
		<token n="идXX" u="155,19" witness="#lem">иде</token>
		<token n="идXX" u="155,19" witness="#likh">иде</token>
		<token n="" u="" witness="#rad"></token>
		<token n="идXX" u="155,19" witness="#shakh">иде</token>
		<token n="идXX" u="155,19" witness="#xle">иде</token>
	</block>
	<block>
		<token n="нXXX" u="155,19" witness="#aka">на</token>
		<token n="нXXX" u="155,19" witness="#bych">на</token>
		<token n="нXXX" u="155,19" witness="#ipa">на</token>
		<token n="нXXX" u="155,19" witness="#lav">на</token>
		<token n="нXXX" u="155,19" witness="#lem">на</token>
		<token n="нXXX" u="155,19" witness="#likh">на</token>
		<token n="нXXX" u="155,19" witness="#rad">на</token>
		<token n="нXXX" u="155,19" witness="#shakh">на</token>
		<token n="нXXX" u="155,19" witness="#xle">на</token>
	</block>
	<block>
		<token n="мзвш" u="155,19" witness="#aka">мазовшаны</token>
		<token n="мзвш" u="155,19" witness="#bych">Мазовшаны,</token>
		<token n="мзвш" u="155,19" witness="#ipa">мазовшаны.</token>
		<token n="мзвш" u="155,19" witness="#lav">мазовшаны. <pb n="52d"/></token>
		<token n="мзвш" u="155,19" witness="#lem">Мазовъшаны,</token>
		<token n="мзвш" u="155,19" witness="#likh">мазовшаны,</token>
		<token n="мзвш" u="155,19" witness="#rad">мазовшаны.</token>
		<token n="мзвш" u="155,19" witness="#shakh">Мазовъшаны,</token>
		<token n="мзвш" u="155,19" witness="#xle">мазовшаны</token>
	</block>
</witnesses>

