{"witnesses":["#aka","#bych","#ipa","#lav","#likh","#rad","#shakh","#xle"],"table":[[[{"u":"","t":"якоже <lb/>","n":"яж00"}],[{"u":"","t":"Якоже","n":"яж00"}],[{"u":"","t":"якоже","n":"яж00"}],[{"u":"","t":"яко<hi rend=\"sup\">ж</hi>","n":"яж00"}],[{"u":"","t":"Яко","n":"я000"}],[{"u":"","t":"я<hi rend=\"sup\">к</hi><lb/>же","n":"яж00"}],[{"u":"","t":"Якоже","n":"яж00"}],[{"u":"","t":"якоже","n":"яж00"}]],[[{"u":"","t":"прр<hi rend=\"sup\">о</hi>кь","n":"пк00"}],[],[{"u":"","t":"пррк<hi rend=\"sup\">о</hi>ъ","n":"пк00"}],[{"u":"","t":"прр҃къ","n":"пк00"}],[{"u":"","t":"же","n":"ж000"}],[{"u":"","t":"прр҃къ","n":"пк00"}],[],[]],[[],[{"u":"","t":"пророкъ","n":"прк0"}],[],[],[{"u":"","t":"пророкъ","n":"прк0"}],[],[{"u":"","t":"пророкъ","n":"прк0"}],[{"u":"","t":"пр<hi rend=\"sup\">о</hi>ркь","n":"прк0"}]],[[{"u":"","t":"гл҃ше·","n":"гш00"}],[{"u":"","t":"глаголаше:","n":"гглш"}],[{"u":"","t":"глш҃е·","n":"гш00"}],[{"u":"","t":"гл҃ше <lb/>","n":"гш00"}],[{"u":"","t":"глаголаше:","n":"гглш"}],[{"u":"","t":"гл҃аше·","n":"гш00"}],[{"u":"","t":"глаголаше:","n":"гглш"}],[{"u":"","t":"гл҃а<lb/>ше.","n":"гш00"}]],[[{"u":"","t":"падете","n":"пдт0"}],[{"u":"","t":"падете","n":"пдт0"}],[{"u":"","t":"паде<lb/>те","n":"пдт0"}],[{"u":"","t":"падете","n":"пдт0"}],[{"u":"","t":"“Падете","n":"“дт0"}],[{"u":"","t":"падеть","n":"пдт0"}],[{"u":"","t":"“Падете","n":"“дт0"}],[{"u":"","t":"падете","n":"пдт0"}]],[[{"u":"","t":"пре<hi rend=\"sup\">д</hi>","n":"пд00"}],[{"u":"","t":"предъ","n":"пд00"}],[{"u":"","t":"предъ","n":"пд00"}],[{"u":"","t":"пре<hi rend=\"sup\">д</hi>","n":"пд00"}],[{"u":"","t":"пред","n":"пд00"}],[{"u":"","t":"пр<hi rend=\"sup\">д</hi>е","n":"пд00"}],[{"u":"","t":"предъ","n":"пд00"}],[{"u":"","t":"пре<hi rend=\"sup\">д</hi>","n":"пд00"}]],[[{"u":"","t":"врагы","n":"вг00"}],[{"u":"","t":"врагы","n":"вг00"}],[{"u":"","t":"враги","n":"вг00"}],[{"u":"","t":"врагы","n":"вг00"}],[{"u":"","t":"врагы","n":"вг00"}],[{"u":"","t":"враги","n":"вг00"}],[{"u":"","t":"врагы","n":"вг00"}],[{"u":"","t":"врагы","n":"вг00"}]],[[{"u":"","t":"<milestone n=\"start\" unit=\"sic\"/>в<milestone n=\"end\" unit=\"sic\"/>ашими·","n":"вшм0"}],[{"u":"","t":"вашими,","n":"вшм0"}],[{"u":"","t":"вашими·","n":"вшм0"}],[{"u":"","t":"вашими·","n":"вшм0"}],[{"u":"","t":"вашими,","n":"вшм0"}],[{"u":"","t":"вашими·","n":"вшм0"}],[{"u":"","t":"вашими,","n":"вшм0"}],[{"u":"","t":"вашими.","n":"вшм0"}]]]}