{"witnesses":["#bych","#lav","#likh"],"table":[[[{"u":"","t":"не","n":"н000"}],[{"u":"","t":"не","n":"н000"}],[{"u":"","t":"не","n":"н000"}]],[[{"u":"","t":"будеть","n":"бдт0"}],[{"u":"","t":"будеть","n":"бдт0"}],[{"u":"","t":"будеть","n":"бдт0"}]],[[{"u":"","t":"ни","n":"н000"}],[{"u":"","t":"ни","n":"н000"}],[{"u":"","t":"ни","n":"н000"}]],[[{"u":"","t":"с","n":"с000"}],[{"u":"","t":"с","n":"с000"}],[{"u":"","t":"с","n":"с000"}]],[[{"u":"","t":"кымъ","n":"км00"}],[{"u":"","t":"кы<hi rend=\"sup\">м</hi>","n":"км00"}],[{"u":"","t":"кым","n":"км00"}]],[[{"u":"","t":"орудья,","n":"одя0"}],[{"u":"","t":"ѡрудья·","n":"одя0"}],[{"u":"","t":"орудья,","n":"одя0"}]],[[{"u":"","t":"аще","n":"а000"}],[{"u":"","t":"а<lb/>ще","n":"а000"}],[{"u":"","t":"аще","n":"а000"}]],[[{"u":"","t":"инѣхъ","n":"их00"}],[{"u":"","t":"инѣ<hi rend=\"sup\">х</hi>","n":"их00"}],[{"u":"","t":"инѣх","n":"их00"}]],[[{"u":"","t":"молитвъ","n":"млтв"}],[{"u":"","t":"млт҃въ","n":"мтв0"}],[{"u":"","t":"молитвъ","n":"млтв"}]],[[{"u":"","t":"не","n":"н000"}],[{"u":"","t":"не","n":"н000"}],[{"u":"","t":"не","n":"н000"}]]]}