<?xml version="1.0" ?>
<witnesses>
	<block>
		<token n="б000" u="" witness="#aka">бо</token>
		<token n="б000" u="" witness="#bych">бо</token>
		<token n="б000" u="" witness="#ipa">бо</token>
		<token n="б000" u="" witness="#lav">бо <lb/></token>
		<token n="б000" u="" witness="#likh">бо</token>
		<token n="б000" u="" witness="#rad">бо</token>
		<token n="б000" u="" witness="#shakh">бо</token>
		<token n="б000" u="" witness="#xle">бо</token>
	</block>
	<block>
		<token n="з̏т0" u="" witness="#aka">ѕрѣ·̏<lb/>ти</token>
		<token n="зт00" u="" witness="#bych">зрѣти</token>
		<token n="зт00" u="" witness="#ipa"><milestone n="start" unit="sic"/>зрѣ<milestone n="end" unit="sic"/><lb/>ти</token>
		<token n="зт00" u="" witness="#lav">зрѣти</token>
		<token n="зт00" u="" witness="#likh">зрѣти</token>
		<token n="зт00" u="" witness="#rad">зрѣти</token>
		<token n="зт00" u="" witness="#shakh">зьрѣти</token>
		<token n="з̏т0" u="" witness="#xle">зрѣ·̏ти</token>
	</block>
	<block>
		<token n="чвкм" u="" witness="#aka">члв҃комъ</token>
		<token n="члвк" u="" witness="#bych">человекомъ</token>
		<token n="чвкм" u="" witness="#ipa">члвк҃омъ·</token>
		<token n="чвкм" u="" witness="#lav">члв҃кмъ·</token>
		<token n="члвк" u="" witness="#likh">человекомъ</token>
		<token n="чкм0" u="" witness="#rad">члк҃мъ.</token>
		<token n="чвкм" u="" witness="#shakh">чловѣкомъ</token>
		<token n="" u="" witness="#xle"></token>
	</block>
	<block>
		<token n="етст" u="" witness="#aka">естьства</token>
		<token n="етст" u="" witness="#bych">естьства</token>
		<token n="етв0" u="" witness="#ipa">ества</token>
		<token n="етст" u="" witness="#lav">естьства</token>
		<token n="етст" u="" witness="#likh">естьства</token>
		<token n="етв0" u="" witness="#rad">е<hi rend="sup">с</hi>ства</token>
		<token n="етст" u="" witness="#shakh">естьства</token>
		<token n="етв0" u="" witness="#xle">е<hi rend="sup">с</hi>ства</token>
	</block>
	<block>
		<token n="аглс" u="" witness="#aka">анг҃льскаго·</token>
		<token n="аглс" u="" witness="#bych">ангельскаго,</token>
		<token n="аглс" u="" witness="#ipa">анг҃льска<lb/>го</token>
		<token n="аглс" u="" witness="#lav">анг҃ль<lb/>скаго·</token>
		<token n="аглс" u="" witness="#likh">ангельскаго,</token>
		<token n="алск" u="" witness="#rad">аггл<hi rend="sup">с</hi>каго·</token>
		<token n="аглс" u="" witness="#shakh">ангельскаго,</token>
		<token n="алск" u="" witness="#xle">аггл<hi rend="sup">с</hi>каго.</token>
	</block>
	<block>
		<token n="" u="" witness="#aka"></token>
		<token n="я000" u="" witness="#bych">яко</token>
		<token n="вдт0" u="" witness="#ipa">вид<milestone n="start" unit="sic"/>ѣ<milestone n="end" unit="sic"/>ти·</token>
		<token n="я000" u="" witness="#lav">яко</token>
		<token n="я000" u="" witness="#likh">яко</token>
		<token n="" u="" witness="#rad"></token>
		<token n="я000" u="" witness="#shakh">яко</token>
		<token n="" u="" witness="#xle"></token>
	</block>
	<block>
		<token n="" u="" witness="#aka"></token>
		<token n="" u="" witness="#bych"></token>
		<token n="а000" u="" witness="#ipa">аще</token>
		<token n="" u="" witness="#lav"></token>
		<token n="" u="" witness="#likh"></token>
		<token n="" u="" witness="#rad"></token>
		<token n="" u="" witness="#shakh"></token>
		<token n="а000" u="" witness="#xle">аще</token>
	</block>
</witnesses>

