{"witnesses": [{"tokens": [{"u": "", "t": "а", "n": "а000"}, {"u": "", "t": "се", "n": "с000"}, {"u": "", "t": "ти", "n": "т000"}, {"u": "", "t": "же", "n": "ж000"}, {"u": "", "t": "словѣни.", "n": "свн0"}, {"u": "", "t": "хровате", "n": "хвт0"}, {"u": "", "t": "бѣлии.", "n": "бл00"}, {"u": "", "t": "и", "n": "и000"}, {"u": "", "t": "серебь.", "n": "срб0"}], "id": "#lav"}, {"tokens": [], "id": "#tro"}, {"tokens": [{"u": "", "t": "а", "n": "а000"}, {"u": "", "t": "се", "n": "с000"}, {"u": "", "t": "ти", "n": "т000"}, {"u": "", "t": "же", "n": "ж000"}, {"u": "", "t": "словѣ<lb/>не<hi rend=\"sup\">ж</hi>", "n": "свнж"}, {"u": "", "t": "хорвате", "n": "хрвт"}, {"u": "", "t": "бѣлии", "n": "бл00"}, {"u": "", "t": "и", "n": "и000"}, {"u": "", "t": "сербь", "n": "срб0"}], "id": "#rad"}, {"tokens": [{"u": "", "t": "а", "n": "а000"}, {"u": "", "t": "се", "n": "с000"}, {"u": "", "t": "ти", "n": "т000"}, {"u": "", "t": "же", "n": "ж000"}, {"u": "", "t": "словѣне", "n": "свн0"}, {"u": "", "t": "хорвате", "n": "хрвт"}, {"u": "", "t": "бѣлїи.", "n": "бл00"}, {"u": "", "t": "и", "n": "и000"}, {"u": "", "t": "сербь. <pb n=\"2v\"/>", "n": "срб0"}], "id": "#aka"}, {"tokens": [{"u": "", "t": "а", "n": "а000"}, {"u": "", "t": "се", "n": "с000"}, {"u": "", "t": "ти", "n": "т000"}, {"u": "", "t": "же", "n": "ж000"}, {"u": "", "t": "словѣ<lb/>н<milestone n=\"start\" unit=\"sic\"/>и<milestone n=\"end\" unit=\"sic\"/>.", "n": "свн0"}, {"u": "", "t": "хорвати", "n": "хрвт"}, {"u": "", "t": "бѣлии.", "n": "бл00"}, {"u": "", "t": "се<lb/>рпь.", "n": "срп0"}], "id": "#ipa"}, {"tokens": [{"u": "", "t": "а", "n": "а000"}, {"u": "", "t": "се", "n": "с000"}, {"u": "", "t": "ти", "n": "т000"}, {"u": "", "t": "же", "n": "ж000"}, {"u": "", "t": "слѡвени. <lb/>", "n": "свн0"}, {"u": "", "t": "хорвати", "n": "хрвт"}, {"u": "", "t": "бѣлїи.", "n": "бл00"}, {"u": "", "t": "и", "n": "и000"}, {"u": "", "t": "серби.", "n": "срб0"}], "id": "#xle"}, {"tokens": [{"u": "", "t": "а", "n": "а000"}, {"u": "", "t": "се", "n": "с000"}, {"u": "", "t": "ти", "n": "т000"}, {"u": "", "t": "же", "n": "ж000"}, {"u": "", "t": "Словѣни:", "n": "свн0"}, {"u": "", "t": "Хорвате", "n": "хрвт"}, {"u": "", "t": "Бѣлии,", "n": "бл00"}, {"u": "", "t": "и", "n": "и000"}, {"u": "", "t": "Серебь", "n": "срб0"}], "id": "#bych"}, {"tokens": [{"u": "", "t": "а", "n": "а000"}, {"u": "", "t": "се", "n": "с000"}, {"u": "", "t": "тиже", "n": "тж00"}, {"u": "", "t": "Словѣне:", "n": "свн0"}, {"u": "", "t": "Хървати", "n": "хвт0"}, {"u": "", "t": "Бѣлии", "n": "бл00"}, {"u": "", "t": "и", "n": "и000"}, {"u": "", "t": "Сьрбь", "n": "сб00"}], "id": "#shakh"}, {"tokens": [{"u": "", "t": "А", "n": "а000"}, {"u": "", "t": "се", "n": "с000"}, {"u": "", "t": "ти", "n": "т000"}, {"u": "", "t": "же", "n": "ж000"}, {"u": "", "t": "словѣни:", "n": "свн0"}, {"u": "", "t": "хровате", "n": "хвт0"}, {"u": "", "t": "бѣлии", "n": "бл00"}, {"u": "", "t": "и", "n": "и000"}, {"u": "", "t": "серебь", "n": "срб0"}], "id": "#likh"}]}