{"witnesses": [{"tokens": [{"u": "62,20", "t": "семь;", "n": "смXX"}, {"u": "62,20", "t": "и", "n": "иXXX"}, {"u": "62,20", "t": "налѣзе", "n": "нлзX"}, {"u": "62,20", "t": "бисьръ", "n": "бсрX"}, {"u": "62,20", "t": "мъногоцѣньнъ,", "n": "мнгц"}, {"u": "62,20", "t": "еже", "n": "ежXX"}], "id": "#lem"}, {"tokens": [{"u": "62,20", "t": "семь.", "n": "смXX"}, {"u": "62,20", "t": "налѣзе <lb/>", "n": "нлзX"}, {"u": "62,20", "t": "бисеръ", "n": "бсрX"}, {"u": "62,20", "t": "многоцѣньныхъ.", "n": "мнгц"}, {"u": "62,20", "t": "еже", "n": "ежXX"}], "id": "#lav"}, {"tokens": [{"u": "62,20", "t": "се<hi rend=\"sup\">м</hi>.", "n": "смXX"}, {"u": "62,20", "t": "и", "n": "иXXX"}, {"u": "62,20", "t": "налѣзе", "n": "нлзX"}, {"u": "62,20", "t": "би<lb/>серъ", "n": "бсрX"}, {"u": "62,20", "t": "мно<hi rend=\"sup\">г</hi>цѣне<hi rend=\"sup\">н</hi>,", "n": "мнгц"}, {"u": "62,20", "t": "е<hi rend=\"sup\">ж</hi>.", "n": "ежXX"}], "id": "#rad"}, {"tokens": [{"u": "62,20", "t": "семь.", "n": "смXX"}, {"u": "62,20", "t": "и", "n": "иXXX"}, {"u": "62,20", "t": "налѣзе <lb/>", "n": "нлзX"}, {"u": "62,20", "t": "бисеръ", "n": "бсрX"}, {"u": "62,20", "t": "многоцѣненъ.", "n": "мнгц"}, {"u": "62,20", "t": "еже", "n": "ежXX"}], "id": "#aka"}, {"tokens": [{"u": "62,20", "t": "семъ. <lb/>", "n": "смXX"}, {"u": "62,20", "t": "и", "n": "иXXX"}, {"u": "62,20", "t": "налѣзе", "n": "нлзX"}, {"u": "62,20", "t": "бисеръ", "n": "бсрX"}, {"u": "62,20", "t": "много<lb/><milestone n=\"start\" unit=\"sic\"/>ц<milestone n=\"end\" unit=\"sic\"/>ѣньныи", "n": "мнгц"}, {"u": "62,20", "t": "еже", "n": "ежXX"}], "id": "#ipa"}, {"tokens": [{"u": "62,20", "t": "се<hi rend=\"sup\">м</hi>.", "n": "смXX"}, {"u": "62,20", "t": "и", "n": "иXXX"}, {"u": "62,20", "t": "налѣзе", "n": "нлзX"}, {"u": "62,20", "t": "би<lb/>серь", "n": "бсрX"}, {"u": "62,20", "t": "многоцѣнныи", "n": "мнгц"}, {"u": "62,20", "t": "еже", "n": "ежXX"}], "id": "#xle"}, {"tokens": [{"u": "62,20", "t": "семъ", "n": "смXX"}, {"u": "62,20", "t": "и", "n": "иXXX"}, {"u": "62,20", "t": "налѣзе", "n": "нлзX"}, {"u": "62,20", "t": "бисеръ", "n": "бсрX"}, {"u": "62,20", "t": "многоцѣнныи", "n": "мнгц"}, {"u": "62,20", "t": "еже", "n": "ежXX"}], "id": "#kom"}, {"tokens": [{"u": "62,20", "t": "семь", "n": "смXX"}, {"u": "62,20", "t": "и", "n": "иXXX"}, {"u": "62,20", "t": "налѣзе", "n": "нлзX"}, {"u": "62,20", "t": "бисеръ", "n": "бсрX"}, {"u": "62,20", "t": "многоцѣнныи", "n": "мнгц"}, {"u": "62,20", "t": "еже", "n": "ежXX"}], "id": "#nak"}, {"tokens": [{"u": "62,20", "t": "семь", "n": "смXX"}, {"u": "62,20", "t": "и", "n": "иXXX"}, {"u": "62,20", "t": "налѣзе", "n": "нлзX"}, {"u": "62,20", "t": "бисеръ", "n": "бсрX"}, {"u": "62,20", "t": "многоцѣнныи", "n": "мнгц"}, {"u": "62,20", "t": "еже", "n": "ежXX"}], "id": "#tol"}, {"tokens": [{"u": "62,20", "t": "семь,", "n": "смXX"}, {"u": "62,20", "t": "налѣзе", "n": "нлзX"}, {"u": "62,20", "t": "бисеръ", "n": "бсрX"}, {"u": "62,20", "t": "многоцѣненъ,", "n": "мнгц"}, {"u": "62,20", "t": "еже", "n": "ежXX"}], "id": "#bych"}, {"tokens": [{"u": "62,20", "t": "семь;", "n": "смXX"}, {"u": "62,20", "t": "и", "n": "иXXX"}, {"u": "62,20", "t": "налѣзе", "n": "нлзX"}, {"u": "62,20", "t": "бисьръ", "n": "бсрX"}, {"u": "62,20", "t": "мъногоцѣньнъ,", "n": "мнгц"}, {"u": "62,20", "t": "еже", "n": "ежXX"}], "id": "#shakh"}, {"tokens": [{"u": "62,20", "t": "семь,", "n": "смXX"}, {"u": "62,20", "t": "налѣзе", "n": "нлзX"}, {"u": "62,20", "t": "бисеръ", "n": "бсрX"}, {"u": "62,20", "t": "многоцѣненъ,", "n": "мнгц"}, {"u": "62,20", "t": "еже", "n": "ежXX"}], "id": "#likh"}]}