{"witnesses": [{"tokens": [{"u": "", "t": "слышавше", "n": "сшвш"}, {"u": "", "t": "се", "n": "с000"}, {"u": "", "t": "ст҃ополкъ.", "n": "сплк"}, {"u": "", "t": "иду<lb/>ща", "n": "ищ00"}, {"u": "", "t": "ярослава.", "n": "яслв"}], "id": "#lav"}, {"tokens": [{"u": "", "t": "слышавъ", "n": "сшв0"}, {"u": "", "t": "с҃тополкъ.", "n": "сплк"}, {"u": "", "t": "идоуща", "n": "ищ00"}, {"u": "", "t": "ярослава:", "n": "яслв"}, {"u": "", "t": "и", "n": "и000"}], "id": "#rad"}, {"tokens": [{"u": "", "t": "слышавь", "n": "сшв0"}, {"u": "", "t": "ст҃ополкъ.", "n": "сплк"}, {"u": "", "t": "идѹща <lb/>", "n": "ищ00"}, {"u": "", "t": "ярослава.", "n": "яслв"}, {"u": "", "t": "и", "n": "и000"}], "id": "#aka"}, {"tokens": [{"u": "", "t": "слышавъ <lb/>", "n": "сшв0"}, {"u": "", "t": "же", "n": "ж000"}, {"u": "", "t": "се", "n": "с000"}, {"u": "", "t": "ст҃ополкъ.", "n": "сплк"}, {"u": "", "t": "идуща", "n": "ищ00"}, {"u": "", "t": "ярослава.", "n": "яслв"}, {"u": "", "t": "и <pb n=\"53c\"/>", "n": "и000"}], "id": "#ipa"}, {"tokens": [{"u": "", "t": "слышав", "n": "сшв0"}, {"u": "", "t": "же", "n": "ж000"}, {"u": "", "t": "се", "n": "с000"}, {"u": "", "t": "ст҃ополкь", "n": "сплк"}, {"u": "", "t": "идуща", "n": "ищ00"}, {"u": "", "t": "ярослава.", "n": "яслв"}], "id": "#xle"}, {"tokens": [{"u": "", "t": "слышавъ", "n": "сшв0"}, {"u": "", "t": "же", "n": "ж000"}, {"u": "", "t": "се", "n": "с000"}, {"u": "", "t": "Святополкъ,", "n": "сятп"}, {"u": "", "t": "идуща", "n": "ищ00"}, {"u": "", "t": "Ярослава,", "n": "яслв"}], "id": "#bych"}, {"tokens": [{"u": "", "t": "Слышавъ", "n": "сшв0"}, {"u": "", "t": "же", "n": "ж000"}, {"u": "", "t": "се", "n": "с000"}, {"u": "", "t": "Святопълкъ", "n": "сятп"}, {"u": "", "t": "идуща", "n": "ищ00"}, {"u": "", "t": "Ярослава,", "n": "яслв"}], "id": "#shakh"}, {"tokens": [{"u": "", "t": "Слышавъ", "n": "сшв0"}, {"u": "", "t": "же", "n": "ж000"}, {"u": "", "t": "Святополкъ,", "n": "сятп"}, {"u": "", "t": "идуща", "n": "ищ00"}, {"u": "", "t": "Ярослава,", "n": "яслв"}], "id": "#likh"}]}