{"witnesses": [{"tokens": [{"u": "232,9", "t": "Въ 20", "n": "вкXX"}, {"u": "232,9", "t": "тогоже", "n": "тгжX"}, {"u": "232,9", "t": "мѣсяца,", "n": "мсцX"}, {"u": "232,9", "t": "въ", "n": "вXXX"}, {"u": "232,9", "t": "пятъкъ,", "n": "пткX"}, {"u": "232,9", "t": "въ", "n": "вXXX"}, {"u": "232,9", "t": "часъ 1", "n": "чсXX"}, {"u": "232,9", "t": "дьне,", "n": "днXX"}], "id": "#lem"}, {"tokens": [{"u": "232,9", "t": "въ·", "n": "вXXX"}, {"u": "232,9", "t": "к҃·", "n": "кXXX"}, {"u": "232,9", "t": "тогоже", "n": "тгжX"}, {"u": "232,9", "t": "мц<hi rend=\"sup\">с</hi>а· <lb/>", "n": "мцсX"}, {"u": "232,9", "t": "в", "n": "вXXX"}, {"u": "232,9", "t": "пѧтокъ·:·", "n": "пткX"}], "id": "#lav"}, {"tokens": [{"u": "232,9", "t": "ц<hi rend=\"sup\">с</hi>ѧ", "n": "цсXX"}, {"u": "232,9", "t": "того<hi rend=\"sup\">ж</hi>.", "n": "тгжX"}, {"u": "232,9", "t": "к҃.", "n": "кXXX"}, {"u": "232,9", "t": "в", "n": "вXXX"}, {"u": "232,9", "t": "пѧ<hi rend=\"sup\">т</hi>.", "n": "птXX"}, {"u": "232,9", "t": "а҃", "n": "аXXX"}, {"u": "232,9", "t": "ча<hi rend=\"sup\">с</hi>", "n": "чсXX"}, {"u": "232,9", "t": "дн҃е.", "n": "днXX"}], "id": "#rad"}, {"tokens": [{"u": "232,9", "t": "Мц<hi rend=\"sup\">с</hi>а", "n": "мцсX"}, {"u": "232,9", "t": "тогоже", "n": "тгжX"}, {"u": "232,9", "t": "·к҃·", "n": "кXXX"}, {"u": "232,9", "t": "в", "n": "вXXX"}, {"u": "232,9", "t": "пѧ<hi rend=\"sup\">т</hi>", "n": "птXX"}, {"u": "232,9", "t": "·а҃· <lb/>", "n": "аXXX"}, {"u": "232,9", "t": "ча<hi rend=\"sup\">с</hi>·", "n": "чсXX"}, {"u": "232,9", "t": "дн҃и·", "n": "днXX"}], "id": "#aka"}, {"tokens": [{"u": "232,9", "t": "въ", "n": "вXXX"}, {"u": "232,9", "t": "·к҃·", "n": "кXXX"}, {"u": "232,9", "t": "тогоже", "n": "тгжX"}, {"u": "232,9", "t": "мц<hi rend=\"sup\">с</hi>а. <lb/>", "n": "мцсX"}, {"u": "232,9", "t": "въ", "n": "вXXX"}, {"u": "232,9", "t": "дн҃ь", "n": "днXX"}, {"u": "232,9", "t": "пѧтокъ·", "n": "пткX"}, {"u": "232,9", "t": "въ", "n": "вXXX"}, {"u": "232,9", "t": "ча<hi rend=\"sup\">с</hi>", "n": "чсXX"}, {"u": "232,9", "t": "·а҃·", "n": "аXXX"}, {"u": "232,9", "t": "дн҃е· <lb/>", "n": "днXX"}], "id": "#ipa"}, {"tokens": [{"u": "232,9", "t": "въ", "n": "вXXX"}, {"u": "232,9", "t": "к҃.", "n": "кXXX"}, {"u": "232,9", "t": "того<hi rend=\"sup\">ж</hi>", "n": "тгжX"}, {"u": "232,9", "t": "мц<hi rend=\"sup\">с</hi>а,", "n": "мцсX"}, {"u": "232,9", "t": "въ", "n": "вXXX"}, {"u": "232,9", "t": "дн҃ь <lb/>", "n": "днXX"}, {"u": "232,9", "t": "пѧто<hi rend=\"sup\">к</hi>.", "n": "пткX"}, {"u": "232,9", "t": "в", "n": "вXXX"}, {"u": "232,9", "t": "ча<hi rend=\"sup\">с</hi>", "n": "чсXX"}, {"u": "232,9", "t": "а҃", "n": "аXXX"}, {"u": "232,9", "t": "дн҃е.", "n": "днXX"}], "id": "#xle"}, {"tokens": [{"u": "232,9", "t": "въ 20", "n": "вкXX"}, {"u": "232,9", "t": "того", "n": "тгXX"}, {"u": "232,9", "t": "же", "n": "жXXX"}, {"u": "232,9", "t": "мѣсяца,", "n": "мсцX"}, {"u": "232,9", "t": "в", "n": "вXXX"}, {"u": "232,9", "t": "пятокъ, 1", "n": "пткX"}, {"u": "232,9", "t": "часъ", "n": "чсXX"}, {"u": "232,9", "t": "дне,", "n": "днXX"}], "id": "#bych"}, {"tokens": [{"u": "232,9", "t": "въ 20", "n": "вкXX"}, {"u": "232,9", "t": "тогоже", "n": "тгжX"}, {"u": "232,9", "t": "мѣсяца,", "n": "мсцX"}, {"u": "232,9", "t": "въ", "n": "вXXX"}, {"u": "232,9", "t": "пятъкъ,", "n": "пткX"}, {"u": "232,9", "t": "въ", "n": "вXXX"}, {"u": "232,9", "t": "часъ 1", "n": "чсXX"}, {"u": "232,9", "t": "дьне,", "n": "днXX"}], "id": "#shakh"}, {"tokens": [{"u": "232,9", "t": "въ 20", "n": "вкXX"}, {"u": "232,9", "t": "того", "n": "тгXX"}, {"u": "232,9", "t": "же", "n": "жXXX"}, {"u": "232,9", "t": "мѣсяца,", "n": "мсцX"}, {"u": "232,9", "t": "в", "n": "вXXX"}, {"u": "232,9", "t": "пятокъ, 1", "n": "пткX"}, {"u": "232,9", "t": "час", "n": "чсXX"}, {"u": "232,9", "t": "дне,", "n": "днXX"}], "id": "#likh"}]}