{"witnesses": [{"tokens": [{"u": "", "t": "посади<hi rend=\"sup\">х</hi>·", "n": "псдх"}, {"u": "", "t": "и", "n": "и000"}, {"u": "", "t": "ярополкъ <lb/>", "n": "яплк"}, {"u": "", "t": "оумре·", "n": "ур00"}, {"u": "", "t": "и", "n": "и000"}, {"u": "", "t": "пакы", "n": "пк00"}, {"u": "", "t": "по", "n": "п000"}, {"u": "", "t": "ѡтни", "n": "он00"}], "id": "#lav"}, {"tokens": [], "id": "#rad"}, {"tokens": [], "id": "#aka"}, {"tokens": [], "id": "#ipa"}, {"tokens": [], "id": "#xle"}, {"tokens": [{"u": "", "t": "посадихъ,", "n": "псдх"}, {"u": "", "t": "и", "n": "и000"}, {"u": "", "t": "Ярополкъ", "n": "яплк"}, {"u": "", "t": "умре.", "n": "ур00"}, {"u": "", "t": "И", "n": "и000"}, {"u": "", "t": "пакы", "n": "пк00"}, {"u": "", "t": "по", "n": "п000"}, {"u": "", "t": "отни", "n": "он00"}], "id": "#bych"}, {"tokens": [{"u": "", "t": "посадих,", "n": "псдх"}, {"u": "", "t": "и", "n": "и000"}, {"u": "", "t": "Ярополкъ", "n": "яплк"}, {"u": "", "t": "умре.", "n": "ур00"}, {"u": "", "t": "И", "n": "и000"}, {"u": "", "t": "пакы", "n": "пк00"}, {"u": "", "t": "по", "n": "п000"}, {"u": "", "t": "отни", "n": "он00"}], "id": "#likh"}]}