{"witnesses": [{"tokens": [{"u": "257,15", "t": "Игоревичю,", "n": "игрв"}, {"u": "257,15", "t": "рекуще", "n": "ркщ0"}, {"u": "257,15", "t": "сице,", "n": "сц00"}, {"u": "257,15", "t": "яко", "n": "ѧк00"}, {"u": "257,15", "t": "“Володимиръ", "n": "“влд"}, {"u": "257,15", "t": "съложилъ", "n": "слжл"}, {"u": "257,15", "t": "ся", "n": "с000"}], "id": "#lem"}, {"tokens": [{"u": "257,15", "t": "игоревичю·", "n": "игрв"}, {"u": "257,15", "t": "рекуще", "n": "ркщ0"}, {"u": "257,15", "t": "сице", "n": "сц00"}, {"u": "257,15", "t": "ꙗко", "n": "ѧк00"}, {"u": "257,15", "t": "во<lb/>лодимеръ", "n": "влдм"}, {"u": "257,15", "t": "сложилсѧ", "n": "слжл"}], "id": "#lav"}, {"tokens": [{"u": "257,15", "t": "игореви<hi rend=\"sup\">ч</hi>.", "n": "игрв"}, {"u": "257,15", "t": "ꙗко", "n": "ѧк00"}, {"u": "257,15", "t": "володиме<lb/>ръ", "n": "влдм"}, {"u": "257,15", "t": "сложилъ<hi rend=\"sup\">с</hi>", "n": "слжл"}], "id": "#rad"}, {"tokens": [{"u": "257,15", "t": "игоревичю·", "n": "игрв"}, {"u": "257,15", "t": "ꙗко", "n": "ѧк00"}, {"u": "257,15", "t": "володимеръ", "n": "влдм"}, {"u": "257,15", "t": "сложи<lb/>лсѧ", "n": "слжл"}], "id": "#aka"}, {"tokens": [{"u": "257,15", "t": "игоревичю·", "n": "игрв"}, {"u": "257,15", "t": "рекуще", "n": "ркщ0"}, {"u": "257,15", "t": "сице·", "n": "сц00"}, {"u": "257,15", "t": "ꙗко <lb/>", "n": "ѧк00"}, {"u": "257,15", "t": "володимеръ", "n": "влдм"}, {"u": "257,15", "t": "сложилъсѧ", "n": "слжл"}], "id": "#ipa"}, {"tokens": [{"u": "257,15", "t": "игоревичю.", "n": "игрв"}, {"u": "257,15", "t": "рекоучи", "n": "ркч0"}, {"u": "257,15", "t": "сице,", "n": "сц00"}, {"u": "257,15", "t": "я<hi rend=\"sup\">к</hi><lb/>", "n": "ѧк00"}, {"u": "257,15", "t": "въл<hi rend=\"sup\">д</hi>о<hi rend=\"sup\">и</hi>меръ", "n": "влдм"}, {"u": "257,15", "t": "е<hi rend=\"sup\">с</hi>", "n": "ес00"}, {"u": "257,15", "t": "сложи<hi rend=\"sup\">л</hi>сѧ", "n": "слжл"}], "id": "#xle"}, {"tokens": [{"u": "257,15", "t": "Игоревичю,", "n": "игрв"}, {"u": "257,15", "t": "рекуще", "n": "ркщ0"}, {"u": "257,15", "t": "сице:", "n": "сц00"}, {"u": "257,15", "t": "“яко", "n": "“к00"}, {"u": "257,15", "t": "Володимеръ", "n": "влдм"}, {"u": "257,15", "t": "сложился", "n": "слжл"}], "id": "#bych"}, {"tokens": [{"u": "257,15", "t": "Игоревичю,", "n": "игрв"}, {"u": "257,15", "t": "рекуще", "n": "ркщ0"}, {"u": "257,15", "t": "сице,", "n": "сц00"}, {"u": "257,15", "t": "яко", "n": "ѧк00"}, {"u": "257,15", "t": "“Володимеръ", "n": "“влд"}, {"u": "257,15", "t": "съложилъся", "n": "слжл"}], "id": "#shakh"}, {"tokens": [{"u": "257,15", "t": "Игоревичю,", "n": "игрв"}, {"u": "257,15", "t": "рекуще", "n": "ркщ0"}, {"u": "257,15", "t": "сице,", "n": "сц00"}, {"u": "257,15", "t": "яко", "n": "ѧк00"}, {"u": "257,15", "t": "“Володимеръ", "n": "“влд"}, {"u": "257,15", "t": "сложился", "n": "слжл"}], "id": "#likh"}]}