{"witnesses": [{"tokens": [{"u": "260,24", "t": "И", "n": "иXXX"}, {"u": "260,24", "t": "се", "n": "сXXX"}, {"u": "260,24", "t": "вълѣзъше", "n": "влзш"}, {"u": "260,24", "t": "друзии", "n": "дрзX"}, {"u": "260,24", "t": "повьргоша", "n": "пврг"}, {"u": "260,24", "t": "и,", "n": "иXXX"}, {"u": "260,24", "t": "и", "n": "иXXX"}, {"u": "260,24", "t": "съвязаша", "n": "свзш"}, {"u": "260,24", "t": "и,", "n": "иXXX"}, {"u": "260,24", "t": "и", "n": "иXXX"}], "id": "#lem"}, {"tokens": [{"u": "260,24", "t": "и", "n": "иXXX"}, {"u": "260,24", "t": "се <lb/>", "n": "сXXX"}, {"u": "260,24", "t": "влѣзше", "n": "влзш"}, {"u": "260,24", "t": "друзии", "n": "дрзX"}, {"u": "260,24", "t": "повергоша", "n": "пврг"}, {"u": "260,24", "t": "и·", "n": "иXXX"}, {"u": "260,24", "t": "и", "n": "иXXX"}, {"u": "260,24", "t": "св<hi rend=\"sup\">ѧ</hi><lb/>заша", "n": "свзш"}, {"u": "260,24", "t": "и·", "n": "иXXX"}, {"u": "260,24", "t": "и", "n": "иXXX"}], "id": "#lav"}, {"tokens": [{"u": "260,24", "t": "и", "n": "иXXX"}, {"u": "260,24", "t": "се", "n": "сXXX"}, {"u": "260,24", "t": "влѣзъше", "n": "влзш"}, {"u": "260,24", "t": "дрѹзии", "n": "дрзX"}, {"u": "260,24", "t": "по<lb/>вергоша", "n": "пврг"}, {"u": "260,24", "t": "и·", "n": "иXXX"}, {"u": "260,24", "t": "и", "n": "иXXX"}, {"u": "260,24", "t": "свѧзаша", "n": "свзш"}, {"u": "260,24", "t": "и·", "n": "иXXX"}, {"u": "260,24", "t": "и", "n": "иXXX"}], "id": "#rad"}, {"tokens": [{"u": "260,24", "t": "и", "n": "иXXX"}, {"u": "260,24", "t": "се", "n": "сXXX"}, {"u": "260,24", "t": "влѣ<lb/>зше", "n": "влзш"}, {"u": "260,24", "t": "дрѹзии", "n": "дрзX"}, {"u": "260,24", "t": "повергоша", "n": "пврг"}, {"u": "260,24", "t": "и·", "n": "иXXX"}, {"u": "260,24", "t": "и", "n": "иXXX"}, {"u": "260,24", "t": "свѧзаша", "n": "свзш"}, {"u": "260,24", "t": "и·", "n": "иXXX"}, {"u": "260,24", "t": "и", "n": "иXXX"}], "id": "#aka"}, {"tokens": [{"u": "260,24", "t": "и", "n": "иXXX"}, {"u": "260,24", "t": "се", "n": "сXXX"}, {"u": "260,24", "t": "влѣзъше", "n": "влзш"}, {"u": "260,24", "t": "друзии", "n": "дрзX"}, {"u": "260,24", "t": "пове<lb/>ргоша", "n": "пврг"}, {"u": "260,24", "t": "и", "n": "иXXX"}, {"u": "260,24", "t": "и", "n": "иXXX"}, {"u": "260,24", "t": "свѧзаша", "n": "свзш"}, {"u": "260,24", "t": "и·", "n": "иXXX"}, {"u": "260,24", "t": "и", "n": "иXXX"}], "id": "#ipa"}, {"tokens": [{"u": "260,24", "t": "и", "n": "иXXX"}, {"u": "260,24", "t": "се", "n": "сXXX"}, {"u": "260,24", "t": "в′ше<hi rend=\"sup\">д</hi>ше", "n": "в′шд"}, {"u": "260,24", "t": "дроуѕїи", "n": "дрзX"}, {"u": "260,24", "t": "и", "n": "иXXX"}, {"u": "260,24", "t": "повер′гоша <lb/>", "n": "пвр′"}, {"u": "260,24", "t": "его.", "n": "егXX"}, {"u": "260,24", "t": "и", "n": "иXXX"}, {"u": "260,24", "t": "свѧзаша", "n": "свзш"}, {"u": "260,24", "t": "его.", "n": "егXX"}, {"u": "260,24", "t": "и", "n": "иXXX"}], "id": "#xle"}, {"tokens": [{"u": "260,24", "t": "И", "n": "иXXX"}, {"u": "260,24", "t": "се", "n": "сXXX"}, {"u": "260,24", "t": "влѣзше", "n": "влзш"}, {"u": "260,24", "t": "друзии", "n": "дрзX"}, {"u": "260,24", "t": "повергоша", "n": "пврг"}, {"u": "260,24", "t": "и,", "n": "иXXX"}, {"u": "260,24", "t": "и", "n": "иXXX"}, {"u": "260,24", "t": "связаша", "n": "свзш"}, {"u": "260,24", "t": "и,", "n": "иXXX"}, {"u": "260,24", "t": "и", "n": "иXXX"}], "id": "#bych"}, {"tokens": [{"u": "260,24", "t": "И", "n": "иXXX"}, {"u": "260,24", "t": "се,", "n": "сXXX"}, {"u": "260,24", "t": "вълѣзъше", "n": "влзш"}, {"u": "260,24", "t": "друзии,", "n": "дрзX"}, {"u": "260,24", "t": "повьргоша", "n": "пврг"}, {"u": "260,24", "t": "и,", "n": "иXXX"}, {"u": "260,24", "t": "и", "n": "иXXX"}, {"u": "260,24", "t": "съвязаша", "n": "свзш"}, {"u": "260,24", "t": "и;", "n": "иXXX"}, {"u": "260,24", "t": "и", "n": "иXXX"}], "id": "#shakh"}, {"tokens": [{"u": "260,24", "t": "И", "n": "иXXX"}, {"u": "260,24", "t": "се", "n": "сXXX"}, {"u": "260,24", "t": "влѣзше", "n": "влзш"}, {"u": "260,24", "t": "друзии", "n": "дрзX"}, {"u": "260,24", "t": "повергоша", "n": "пврг"}, {"u": "260,24", "t": "и,", "n": "иXXX"}, {"u": "260,24", "t": "и", "n": "иXXX"}, {"u": "260,24", "t": "связаша", "n": "свзш"}, {"u": "260,24", "t": "и,", "n": "иXXX"}, {"u": "260,24", "t": "и", "n": "иXXX"}], "id": "#likh"}]}