<?xml version="1.0" ?>
<witnesses>
	<block>
		<token n="ко" u="43,19." witness="#aka">ко</token>
		<token n="ко" u="43,19." witness="#bych">ко</token>
		<token n="кь" u="43,19." witness="#ipa">къ</token>
		<token n="ко" u="43,19." witness="#lav">ко</token>
		<token n="кь" u="43,19." witness="#lem">къ</token>
		<token n="ко" u="43,19." witness="#likh">ко</token>
		<token n="ко" u="43,19." witness="#rad">ко</token>
		<token n="кь" u="43,19." witness="#shakh">къ</token>
		<token n="кь" u="43,19." witness="#xle">къ</token>
	</block>
	<block>
		<token n="цргр" u="43,19." witness="#aka">ц҃рюградѹ.</token>
		<token n="цргр" u="43,19." witness="#bych">Царюграду</token>
		<token n="црсг" u="43,19." witness="#ipa">цр<hi rend="sup">с</hi>ю<lb/>граду</token>
		<token n="цргр" u="43,19." witness="#lav">ц҃рюграду</token>
		<token n="цсрг" u="43,19." witness="#lem">Цьсарюграду</token>
		<token n="цргр" u="43,19." witness="#likh">Царюграду</token>
		<token n="цргр" u="43,19." witness="#rad">ц҃рюградѹ.</token>
		<token n="цсрг" u="43,19." witness="#shakh">Цѣсарюграду</token>
		<token n="цргр" u="43,19." witness="#xle">ц҃рюгра<hi rend="sup">д</hi>у. <lb/></token>
	</block>
	<block>
		<token n="в" u="43,19." witness="#aka">в</token>
		<token n="вь" u="43,19." witness="#bych">въ</token>
		<token n="вь" u="43,19." witness="#ipa">въ</token>
		<token n="вь" u="43,19." witness="#lav">въ <lb/></token>
		<token n="вь" u="43,19." witness="#lem">въ</token>
		<token n="вь" u="43,19." witness="#likh">въ</token>
		<token n="в" u="43,19." witness="#rad">в</token>
		<token n="вь" u="43,19." witness="#shakh">въ</token>
		<token n="в" u="43,19." witness="#xle">в</token>
	</block>
	<block>
		<token n="сл" u="43,19." witness="#aka">силе</token>
		<token n="сл" u="43,19." witness="#bych">силѣ</token>
		<token n="сл" u="43,19." witness="#ipa">силѣ</token>
		<token n="сл" u="43,19." witness="#lav">силѣ</token>
		<token n="сл" u="43,19." witness="#lem">силѣ</token>
		<token n="сл" u="43,19." witness="#likh">силѣ</token>
		<token n="сл" u="43,19." witness="#rad">силе</token>
		<token n="сл" u="43,19." witness="#shakh">силѣ</token>
		<token n="сл" u="43,19." witness="#xle">силѣ</token>
	</block>
	<block>
		<token n="" u="43,19." witness="#aka"></token>
		<token n="вь" u="43,19." witness="#bych">въ</token>
		<token n="" u="43,19." witness="#ipa"></token>
		<token n="вь" u="43,19." witness="#lav">въ</token>
		<token n="" u="43,19." witness="#lem"></token>
		<token n="вь" u="43,19." witness="#likh">въ</token>
		<token n="" u="43,19." witness="#rad"></token>
		<token n="" u="43,19." witness="#shakh"></token>
		<token n="" u="43,19." witness="#xle"></token>
	</block>
	<block>
		<token n="влц" u="43,19." witness="#aka">велице.</token>
		<token n="влц" u="43,19." witness="#bych">велицѣ,</token>
		<token n="влц" u="43,19." witness="#ipa">велицѣ</token>
		<token n="влц" u="43,19." witness="#lav">велицѣ</token>
		<token n="влц" u="43,19." witness="#lem">велицѣ</token>
		<token n="влц" u="43,19." witness="#likh">велицѣ,</token>
		<token n="влц" u="43,19." witness="#rad">велице</token>
		<token n="влц" u="43,19." witness="#shakh">велицѣ</token>
		<token n="влц" u="43,19." witness="#xle">велици</token>
	</block>
	<block>
		<token n="и" u="43,19." witness="#aka">и</token>
		<token n="" u="43,19." witness="#bych"></token>
		<token n="и" u="43,19." witness="#ipa">и</token>
		<token n="" u="43,19." witness="#lav"></token>
		<token n="и" u="43,19." witness="#lem">и</token>
		<token n="" u="43,19." witness="#likh"></token>
		<token n="и" u="43,19." witness="#rad">и</token>
		<token n="и" u="43,19." witness="#shakh">и</token>
		<token n="и" u="43,19." witness="#xle">и</token>
	</block>
	<block>
		<token n="в" u="43,19." witness="#aka">в</token>
		<token n="в" u="43,19." witness="#bych">в</token>
		<token n="в" u="43,19." witness="#ipa">в</token>
		<token n="в" u="43,19." witness="#lav">в</token>
		<token n="вь" u="43,19." witness="#lem">въ</token>
		<token n="в" u="43,19." witness="#likh">в</token>
		<token n="в" u="43,19." witness="#rad">в</token>
		<token n="вь" u="43,19." witness="#shakh">въ</token>
		<token n="в" u="43,19." witness="#xle">в</token>
	</block>
	<block>
		<token n="грдс" u="43,19." witness="#aka">гордости.</token>
		<token n="грдс" u="43,19." witness="#bych">гордости,</token>
		<token n="грдс" u="43,19." witness="#ipa">горъ<lb/>дости.</token>
		<token n="грдс" u="43,19." witness="#lav">гордости.</token>
		<token n="грдс" u="43,19." witness="#lem">гьрдости.</token>
		<token n="грдс" u="43,19." witness="#likh">гордости,</token>
		<token n="грдс" u="43,19." witness="#rad">гордости</token>
		<token n="грдс" u="43,19." witness="#shakh">гьрдости.</token>
		<token n="грдс" u="43,19." witness="#xle">гордости.</token>
	</block>
</witnesses>

