{"witnesses":["#aka","#bych","#ipa","#kom","#lav","#lem","#likh","#rad","#shakh","#tol","#xle"],"table":[[[{"u":"64,21.","t":"В","n":"в"}],[{"u":"64,21.","t":"В","n":"в"}],[{"u":"64,21.","t":"В","n":"в"}],[{"u":"64,21.","t":"в","n":"в"}],[{"u":"64,21.","t":"В","n":"в"}],[{"u":"64,21.","t":"Въ","n":"в"}],[{"u":"64,21.","t":"В","n":"в"}],[{"u":"64,21.","t":"В","n":"в"}],[{"u":"64,21.","t":"Въ","n":"в"}],[{"u":"64,21.","t":"в","n":"в"}],[{"u":"64,21.","t":"В","n":"в"}]],[[{"u":"64,21.","t":"лѣ<hi rend=\"sup\">т</hi>.","n":"лт"}],[{"u":"64,21.","t":"лѣто","n":"лт"}],[{"u":"64,21.","t":"лѣто.","n":"лт"}],[{"u":"64,21.","t":"лѣто","n":"лт"}],[{"u":"64,21.","t":"лѣ<hi rend=\"sup\">т</hi>.","n":"лт"}],[{"u":"64,21.","t":"лѣто","n":"лт"}],[{"u":"64,21.","t":"лѣто","n":"лт"}],[{"u":"64,21.","t":"лѣ<hi rend=\"sup\">т</hi>","n":"лт"}],[{"u":"64,21.","t":"лѣто","n":"лт"}],[{"u":"64,21.","t":"лѣто","n":"лт"}],[{"u":"64,21.","t":"лѣ<hi rend=\"sup\">т</hi>","n":"лт"}]],[[{"u":"64,21.","t":"҂ѕ҃.у҃.о҃а.","n":"҂з"}],[{"u":"64,21.","t":"6471.","n":"҂з"}],[{"u":"64,21.","t":"҂ѕ҃.у҃.о҃а·:· <lb/><pb n=\"25d\"/>","n":"҂з"}],[{"u":"64,21.","t":"6471.","n":"҂з"}],[{"u":"64,21.","t":"҂ѕ҃.у҃.о҃а·:·","n":"҂з"}],[{"u":"64,21.","t":"6471.","n":"҂з"}],[{"u":"64,21.","t":"6471.","n":"҂з"}],[{"u":"64,21.","t":"҂ѕ҃","n":"҂з"}],[{"u":"64,21.","t":"6471.","n":"҂з"}],[{"u":"64,21.","t":"6471.","n":"҂з"}],[{"u":"64,21.","t":"҂ѕ҃.у҃.о҃а.","n":"҂з"}]],[[],[],[],[],[],[],[],[{"u":"64,21.","t":"у҃.о҃а. <lb/>","n":"у"}],[],[],[]]]}