{"witnesses":["#aka","#bych","#ipa","#kom","#lav","#lem","#likh","#nak","#rad","#shakh","#tol","#xle"],"table":[[[],[],[{"u":"136,13.","t":"приꙗлъ","n":"прл"}],[],[{"u":"136,13.","t":"стрт<hi rend=\"sup\">с</hi>ь","n":"стрт"}],[],[],[{"u":"136,13.","t":"ту","n":"ту"}],[],[],[{"u":"136,13.","t":"ту","n":"ту"}],[]],[[],[],[],[],[],[],[],[{"u":"136,13.","t":"же","n":"же"}],[],[],[{"u":"136,13.","t":"же","n":"же"}],[]],[[{"u":"136,13.","t":"стр<hi rend=\"sup\">с</hi>ть","n":"стрс"}],[{"u":"136,13.","t":"страсть","n":"стрс"}],[{"u":"136,13.","t":"стр<hi rend=\"sup\">с</hi>ть.","n":"стрс"}],[{"u":"136,13.","t":"страсть","n":"стрс"}],[],[{"u":"136,13.","t":"страсть","n":"стрс"}],[{"u":"136,13.","t":"страсть","n":"стрс"}],[{"u":"136,13.","t":"страсть","n":"стрс"}],[{"u":"136,13.","t":"стр<hi rend=\"sup\">с</hi>ть","n":"стрс"}],[{"u":"136,13.","t":"страсть","n":"стрс"}],[{"u":"136,13.","t":"страсть","n":"стрс"}],[{"u":"136,13.","t":"стр<hi rend=\"sup\">с</hi>ть.","n":"стрс"}]],[[{"u":"136,13.","t":"прїꙗлъ.","n":"прл"}],[{"u":"136,13.","t":"приялъ;","n":"прл"}],[],[{"u":"136,13.","t":"приꙗти","n":"прт"}],[{"u":"136,13.","t":"приꙗлъ.","n":"прл"}],[{"u":"136,13.","t":"приялъ.","n":"прл"}],[{"u":"136,13.","t":"приялъ.","n":"прл"}],[],[{"u":"136,13.","t":"приꙗлъ.","n":"прл"}],[{"u":"136,13.","t":"приялъ;","n":"прл"}],[],[]],[[{"u":"136,13.","t":"лѹче","n":"лч"}],[{"u":"136,13.","t":"луче","n":"лч"}],[{"u":"136,13.","t":"луче","n":"лч"}],[{"u":"136,13.","t":"и","n":"и"}],[{"u":"136,13.","t":"лу<lb/>че","n":"лч"}],[{"u":"136,13.","t":"Луче","n":"лч"}],[{"u":"136,13.","t":"Луче","n":"лч"}],[{"u":"136,13.","t":"и","n":"и"}],[{"u":"136,13.","t":"лоу<hi rend=\"sup\">ч</hi>","n":"лч"}],[{"u":"136,13.","t":"луче","n":"лч"}],[{"u":"136,13.","t":"и","n":"и"}],[{"u":"136,13.","t":"лоуче","n":"лч"}]],[[{"u":"136,13.","t":"бы","n":"би"}],[{"u":"136,13.","t":"бы","n":"би"}],[{"u":"136,13.","t":"бы","n":"би"}],[],[{"u":"136,13.","t":"бо","n":"бо"}],[{"u":"136,13.","t":"бы","n":"би"}],[{"u":"136,13.","t":"бы","n":"би"}],[],[{"u":"136,13.","t":"бы","n":"би"}],[{"u":"136,13.","t":"бы","n":"би"}],[],[{"u":"136,13.","t":"бо","n":"бо"}]],[[{"u":"136,13.","t":"ми","n":"ми"}],[{"u":"136,13.","t":"ми","n":"ми"}],[{"u":"136,13.","t":"ми <lb/>","n":"ми"}],[],[{"u":"136,13.","t":"ми","n":"ми"}],[{"u":"136,13.","t":"ми","n":"ми"}],[{"u":"136,13.","t":"ми","n":"ми"}],[],[{"u":"136,13.","t":"ми","n":"ми"}],[{"u":"136,13.","t":"ми","n":"ми"}],[],[{"u":"136,13.","t":"ми","n":"ми"}]],[[],[{"u":"136,13.","t":"было","n":"бл"}],[],[],[{"u":"136,13.","t":"было","n":"бл"}],[],[{"u":"136,13.","t":"было","n":"бл"}],[],[],[{"u":"136,13.","t":"было","n":"бл"}],[],[]],[[{"u":"136,13.","t":"с","n":"с"}],[{"u":"136,13.","t":"с","n":"с"}],[{"u":"136,13.","t":"с","n":"с"}],[{"u":"136,13.","t":"с","n":"с"}],[{"u":"136,13.","t":"с","n":"с"}],[{"u":"136,13.","t":"съ","n":"сь"}],[{"u":"136,13.","t":"с","n":"с"}],[{"u":"136,13.","t":"с","n":"с"}],[{"u":"136,13.","t":"с","n":"с"}],[{"u":"136,13.","t":"съ","n":"сь"}],[{"u":"136,13.","t":"с","n":"с"}],[{"u":"136,13.","t":"с","n":"с"}]],[[{"u":"136,13.","t":"то<lb/>бою","n":"тб"}],[{"u":"136,13.","t":"тобою","n":"тб"}],[{"u":"136,13.","t":"тобою","n":"тб"}],[{"u":"136,13.","t":"тобою","n":"тб"}],[{"u":"136,13.","t":"тобою","n":"тб"}],[{"u":"136,13.","t":"тобою","n":"тб"}],[{"u":"136,13.","t":"тобою","n":"тб"}],[{"u":"136,13.","t":"тобою","n":"тб"}],[{"u":"136,13.","t":"тобою","n":"тб"}],[{"u":"136,13.","t":"тобою","n":"тб"}],[{"u":"136,13.","t":"тобою","n":"тб"}],[{"u":"136,13.","t":"тобою <lb/>","n":"тб"}]],[[{"u":"136,13.","t":"оумрети.","n":"умрт"}],[{"u":"136,13.","t":"умрети,","n":"умрт"}],[{"u":"136,13.","t":"оумрети","n":"умрт"}],[{"u":"136,13.","t":"жити","n":"жт"}],[{"u":"136,13.","t":"жити.","n":"жт"}],[{"u":"136,13.","t":"умрети,","n":"умрт"}],[{"u":"136,13.","t":"умрети,","n":"умрт"}],[{"u":"136,13.","t":"жити","n":"жт"}],[{"u":"136,13.","t":"оумрети.","n":"умрт"}],[{"u":"136,13.","t":"умрети,","n":"умрт"}],[{"u":"136,13.","t":"жити","n":"жт"}],[{"u":"136,13.","t":"оумрети.","n":"умрт"}]]]}