{"witnesses":["#aka","#bych","#ipa","#lav","#lem","#likh","#rad","#shakh","#xle"],"table":[[[{"u":"206,25.","t":"началъ","n":"нчл"}],[{"u":"206,25.","t":"началъ","n":"нчл"}],[{"u":"206,25.","t":"началъ. <lb/>","n":"нчл"}],[{"u":"206,25.","t":"началъ","n":"нчл"}],[{"u":"206,25.","t":"началъ","n":"нчл"}],[{"u":"206,25.","t":"началъ","n":"нчл"}],[{"u":"206,25.","t":"на<hi rend=\"sup\">ч</hi>","n":"нч"}],[{"u":"206,25.","t":"началъ","n":"нчл"}],[{"u":"206,25.","t":"началъ","n":"нчл"}]],[[{"u":"206,25.","t":"за<hi rend=\"sup\">д</hi>ти.","n":"здт"}],[{"u":"206,25.","t":"здати","n":"здт"}],[{"u":"206,25.","t":"здати","n":"здт"}],[{"u":"206,25.","t":"здати","n":"здт"}],[{"u":"206,25.","t":"зьдати,","n":"здт"}],[{"u":"206,25.","t":"здати","n":"здт"}],[{"u":"206,25.","t":"зда<lb/>ти.","n":"здт"}],[{"u":"206,25.","t":"зьдати","n":"здт"}],[{"u":"206,25.","t":"здати.","n":"здт"}]],[[{"u":"206,25.","t":"де<hi rend=\"sup\">к</hi>","n":"дк"}],[{"u":"206,25.","t":"преже,","n":"прж"}],[{"u":"206,25.","t":"мц҃ѧ.","n":"мц"}],[{"u":"206,25.","t":"пре<hi rend=\"sup\">ж</hi> <lb/>","n":"прж"}],[],[{"u":"206,25.","t":"преже,","n":"прж"}],[],[{"u":"206,25.","t":"преже,","n":"прж"}],[]],[[],[{"u":"206,25.","t":"мѣсяца","n":"мсц"}],[{"u":"206,25.","t":"декѧ<hi rend=\"sup\">б</hi>.","n":"дкб"}],[{"u":"206,25.","t":"мц<hi rend=\"sup\">с</hi>а","n":"мцс"}],[{"u":"206,25.","t":"мѣсяца","n":"мсц"}],[{"u":"206,25.","t":"мѣсяца","n":"мсц"}],[],[{"u":"206,25.","t":"мѣсяца","n":"мсц"}],[{"u":"206,25.","t":"мц<hi rend=\"sup\">с</hi>а","n":"мцс"}]],[[],[{"u":"206,25.","t":"декабря","n":"дкбр"}],[],[{"u":"206,25.","t":"декабрѧ.","n":"дкбр"}],[{"u":"206,25.","t":"декабря","n":"дкбр"}],[{"u":"206,25.","t":"декабря","n":"дкбр"}],[{"u":"206,25.","t":"декабрѧ","n":"дкбр"}],[{"u":"206,25.","t":"декабря","n":"дкбр"}],[{"u":"206,25.","t":"декабрѧ","n":"дкбр"}]],[[],[{"u":"206,25.","t":"въ","n":"вь"}],[{"u":"206,25.","t":"въ","n":"вь"}],[{"u":"206,25.","t":"въ","n":"вь"}],[{"u":"206,25.","t":"въ","n":"вь"}],[{"u":"206,25.","t":"въ","n":"вь"}],[],[{"u":"206,25.","t":"въ","n":"вь"}],[{"u":"206,25.","t":"въ","n":"вь"}]],[[{"u":"206,25.","t":".е҃.","n":"е"}],[{"u":"206,25.","t":"5","n":"е"}],[{"u":"206,25.","t":".е҃. <lb/>","n":"е"}],[{"u":"206,25.","t":".е҃.","n":"е"}],[{"u":"206,25.","t":"5","n":"е"}],[{"u":"206,25.","t":"5","n":"е"}],[{"u":"206,25.","t":".е҃.","n":"е"}],[{"u":"206,25.","t":"5","n":"е"}],[{"u":"206,25.","t":".е҃.","n":"е"}]],[[{"u":"206,25.","t":"дн҃ь:·","n":"дн"}],[{"u":"206,25.","t":"день.","n":"дн"}],[{"u":"206,25.","t":"дн҃ь.","n":"дн"}],[{"u":"206,25.","t":"дн҃ь.","n":"дн"}],[{"u":"206,25.","t":"дьнь.","n":"дн"}],[{"u":"206,25.","t":"день.","n":"дн"}],[{"u":"206,25.","t":"дн҃ь:- <lb/>","n":"дн"}],[{"u":"206,25.","t":"дьнь.","n":"дн"}],[{"u":"206,25.","t":"де<hi rend=\"sup\">н</hi>. <lb/>","n":"дн"}]]]}